Compiled from "CustomClassLoader2.java"
public class classes.test.CustomClassLoader2 extends java.lang.ClassLoader
  SourceFile: "CustomClassLoader2.java"
  InnerClass: 
   public #84= #54 of #1; //CustomException=class classes/test/CustomClassLoader2$CustomException of class classes/test/CustomClassLoader2
   public #86= #56 of #1; //CustomException2=class classes/test/CustomClassLoader2$CustomException2 of class classes/test/CustomClassLoader2
   #79; //class classes/test/CustomClassLoader2$1
   #81; //class classes/test/CustomClassLoader2$2
  minor version: 0
  major version: 50
  Constant pool:
const #1 = class	#123;	//  classes/test/CustomClassLoader2
const #2 = Method	#17.#124;	//  java/lang/Class.getClassLoader:()Ljava/lang/ClassLoader;
const #3 = Method	#83.#125;	//  java/lang/ClassLoader."<init>":(Ljava/lang/ClassLoader;)V
const #4 = class	#126;	//  java/util/Hashtable
const #5 = Method	#4.#127;	//  java/util/Hashtable."<init>":()V
const #6 = Field	#1.#128;	//  classes/test/CustomClassLoader2.classes:Ljava/util/Hashtable;
const #7 = Field	#129.#130;	//  java/lang/System.out:Ljava/io/PrintStream;
const #8 = class	#131;	//  java/lang/StringBuilder
const #9 = Method	#8.#127;	//  java/lang/StringBuilder."<init>":()V
const #10 = String	#132;	//  Loading class 
const #11 = Method	#8.#133;	//  java/lang/StringBuilder.append:(Ljava/lang/String;)Ljava/lang/StringBuilder;
const #12 = Method	#8.#134;	//  java/lang/StringBuilder.toString:()Ljava/lang/String;
const #13 = Method	#135.#136;	//  java/io/PrintStream.println:(Ljava/lang/String;)V
const #14 = Method	#1.#137;	//  classes/test/CustomClassLoader2.findClass:(Ljava/lang/String;)Ljava/lang/Class;
const #15 = String	#138;	//  Finding class 
const #16 = Method	#4.#139;	//  java/util/Hashtable.get:(Ljava/lang/Object;)Ljava/lang/Object;
const #17 = class	#140;	//  java/lang/Class
const #18 = String	#141;	//  classes/test/data/CustomClassLoader2/
const #19 = Field	#33.#142;	//  java/io/File.separatorChar:C
const #20 = Method	#143.#144;	//  java/lang/String.replace:(CC)Ljava/lang/String;
const #21 = String	#145;	//  .class
const #22 = Method	#1.#146;	//  classes/test/CustomClassLoader2.loadClassData:(Ljava/lang/String;)[B
const #23 = String	#147;	//  Defining class 
const #24 = Method	#1.#148;	//  classes/test/CustomClassLoader2.defineClass:(Ljava/lang/String;[BIILjava/security/ProtectionDomain;)Ljava/lang/Class;
const #25 = String	#149;	//  Registering class 
const #26 = Method	#4.#150;	//  java/util/Hashtable.put:(Ljava/lang/Object;Ljava/lang/Object;)Ljava/lang/Object;
const #27 = String	#151;	//  Found class. Returning.
const #28 = class	#152;	//  java/lang/Exception
const #29 = String	#153;	//  Couldn't get the class ourselves!
const #30 = String	#154;	//  Getting the system class.
const #31 = Method	#1.#155;	//  classes/test/CustomClassLoader2.findSystemClass:(Ljava/lang/String;)Ljava/lang/Class;
const #32 = String	#156;	//  Couldn't find. Returning null.
const #33 = class	#157;	//  java/io/File
const #34 = Method	#33.#158;	//  java/io/File."<init>":(Ljava/lang/String;)V
const #35 = Method	#33.#159;	//  java/io/File.length:()J
const #36 = class	#160;	//  java/io/FileInputStream
const #37 = Method	#36.#161;	//  java/io/FileInputStream."<init>":(Ljava/io/File;)V
const #38 = class	#162;	//  java/io/DataInputStream
const #39 = Method	#38.#163;	//  java/io/DataInputStream."<init>":(Ljava/io/InputStream;)V
const #40 = Method	#38.#164;	//  java/io/DataInputStream.readFully:([B)V
const #41 = Method	#38.#165;	//  java/io/DataInputStream.close:()V
const #42 = Field	#1.#166;	//  classes/test/CustomClassLoader2.MethodNameComparator:Ljava/util/Comparator;
const #43 = Method	#167.#168;	//  java/util/Arrays.sort:([Ljava/lang/Object;Ljava/util/Comparator;)V
const #44 = String	#169;	//  \tMethod: 
const #45 = Method	#170.#171;	//  java/lang/reflect/Method.getName:()Ljava/lang/String;
const #46 = String	#172;	//  There are 
const #47 = Method	#8.#173;	//  java/lang/StringBuilder.append:(I)Ljava/lang/StringBuilder;
const #48 = String	#174;	//   interfaces!
const #49 = Field	#1.#175;	//  classes/test/CustomClassLoader2.ClassNameComparator:Ljava/util/Comparator;
const #50 = String	#176;	//  Interface: 
const #51 = Method	#17.#171;	//  java/lang/Class.getName:()Ljava/lang/String;
const #52 = Method	#17.#177;	//  java/lang/Class.getMethods:()[Ljava/lang/reflect/Method;
const #53 = Method	#1.#178;	//  classes/test/CustomClassLoader2.printMethods:([Ljava/lang/reflect/Method;)V
const #54 = class	#179;	//  classes/test/CustomClassLoader2$CustomException
const #55 = Method	#54.#127;	//  classes/test/CustomClassLoader2$CustomException."<init>":()V
const #56 = class	#180;	//  classes/test/CustomClassLoader2$CustomException2
const #57 = Method	#56.#127;	//  classes/test/CustomClassLoader2$CustomException2."<init>":()V
const #58 = Method	#1.#127;	//  classes/test/CustomClassLoader2."<init>":()V
const #59 = String	#181;	//  Loading Dog...
const #60 = String	#182;	//  classes.test.Dog
const #61 = Method	#1.#183;	//  classes/test/CustomClassLoader2.loadClass:(Ljava/lang/String;)Ljava/lang/Class;
const #62 = String	#184;	//  Dog's methods
const #63 = String	#185;	//  Getting Dog's interfaces...
const #64 = Method	#17.#186;	//  java/lang/Class.getInterfaces:()[Ljava/lang/Class;
const #65 = Method	#1.#187;	//  classes/test/CustomClassLoader2.printInterfaces:([Ljava/lang/Class;)V
const #66 = String	#188;	//  Now let's resolve dog...
const #67 = Method	#1.#189;	//  classes/test/CustomClassLoader2.resolveClass:(Ljava/lang/Class;)V
const #68 = Method	#17.#190;	//  java/lang/Class.getSuperclass:()Ljava/lang/Class;
const #69 = String	#191;	//  Super class: 
const #70 = String	#192;	//  classes.test.CatchBootstrapExceptions
const #71 = String	#193;	//  catcher
const #72 = class	#194;	//  java/lang/Character
const #73 = Method	#17.#195;	//  java/lang/Class.getMethod:(Ljava/lang/String;[Ljava/lang/Class;)Ljava/lang/reflect/Method;
const #74 = String	#196;	//  Obtained catcher Method.
const #75 = Method	#170.#197;	//  java/lang/reflect/Method.setAccessible:(Z)V
const #76 = class	#198;	//  java/lang/Object
const #77 = Method	#72.#199;	//  java/lang/Character.valueOf:(C)Ljava/lang/Character;
const #78 = Method	#170.#200;	//  java/lang/reflect/Method.invoke:(Ljava/lang/Object;[Ljava/lang/Object;)Ljava/lang/Object;
const #79 = class	#201;	//  classes/test/CustomClassLoader2$1
const #80 = Method	#79.#127;	//  classes/test/CustomClassLoader2$1."<init>":()V
const #81 = class	#203;	//  classes/test/CustomClassLoader2$2
const #82 = Method	#81.#127;	//  classes/test/CustomClassLoader2$2."<init>":()V
const #83 = class	#204;	//  java/lang/ClassLoader
const #84 = Asciz	CustomException;
const #85 = Asciz	InnerClasses;
const #86 = Asciz	CustomException2;
const #87 = Asciz	classes;
const #88 = Asciz	Ljava/util/Hashtable;;
const #89 = Asciz	ClassNameComparator;
const #90 = Asciz	Ljava/util/Comparator;;
const #91 = Asciz	Signature;
const #92 = Asciz	Ljava/util/Comparator<Ljava/lang/Class;>;;
const #93 = Asciz	MethodNameComparator;
const #94 = Asciz	Ljava/util/Comparator<Ljava/lang/reflect/Method;>;;
const #95 = Asciz	<init>;
const #96 = Asciz	()V;
const #97 = Asciz	Code;
const #98 = Asciz	LineNumberTable;
const #99 = Asciz	loadClass;
const #100 = Asciz	(Ljava/lang/String;)Ljava/lang/Class;;
const #101 = Asciz	Exceptions;
const #102 = class	#205;	//  java/lang/ClassNotFoundException
const #103 = Asciz	findClass;
const #104 = Asciz	StackMapTable;
const #105 = class	#140;	//  java/lang/Class
const #106 = class	#152;	//  java/lang/Exception
const #107 = Asciz	loadClassData;
const #108 = Asciz	(Ljava/lang/String;)[B;
const #109 = class	#206;	//  java/io/IOException
const #110 = Asciz	printMethods;
const #111 = Asciz	([Ljava/lang/reflect/Method;)V;
const #112 = class	#207;	//  "[Ljava/lang/reflect/Method;"
const #113 = Asciz	printInterfaces;
const #114 = Asciz	([Ljava/lang/Class;)V;
const #115 = class	#208;	//  "[Ljava/lang/Class;"
const #116 = Asciz	throwBootstrapException;
const #117 = Asciz	throwBootstrapException2;
const #118 = Asciz	main;
const #119 = Asciz	([Ljava/lang/String;)V;
const #120 = Asciz	<clinit>;
const #121 = Asciz	SourceFile;
const #122 = Asciz	CustomClassLoader2.java;
const #123 = Asciz	classes/test/CustomClassLoader2;
const #124 = NameAndType	#209:#210;//  getClassLoader:()Ljava/lang/ClassLoader;
const #125 = NameAndType	#95:#211;//  "<init>":(Ljava/lang/ClassLoader;)V
const #126 = Asciz	java/util/Hashtable;
const #127 = NameAndType	#95:#96;//  "<init>":()V
const #128 = NameAndType	#87:#88;//  classes:Ljava/util/Hashtable;
const #129 = class	#212;	//  java/lang/System
const #130 = NameAndType	#213:#214;//  out:Ljava/io/PrintStream;
const #131 = Asciz	java/lang/StringBuilder;
const #132 = Asciz	Loading class ;
const #133 = NameAndType	#215:#216;//  append:(Ljava/lang/String;)Ljava/lang/StringBuilder;
const #134 = NameAndType	#217:#218;//  toString:()Ljava/lang/String;
const #135 = class	#219;	//  java/io/PrintStream
const #136 = NameAndType	#220:#221;//  println:(Ljava/lang/String;)V
const #137 = NameAndType	#103:#100;//  findClass:(Ljava/lang/String;)Ljava/lang/Class;
const #138 = Asciz	Finding class ;
const #139 = NameAndType	#222:#223;//  get:(Ljava/lang/Object;)Ljava/lang/Object;
const #140 = Asciz	java/lang/Class;
const #141 = Asciz	classes/test/data/CustomClassLoader2/;
const #142 = NameAndType	#224:#225;//  separatorChar:C
const #143 = class	#226;	//  java/lang/String
const #144 = NameAndType	#227:#228;//  replace:(CC)Ljava/lang/String;
const #145 = Asciz	.class;
const #146 = NameAndType	#107:#108;//  loadClassData:(Ljava/lang/String;)[B
const #147 = Asciz	Defining class ;
const #148 = NameAndType	#229:#230;//  defineClass:(Ljava/lang/String;[BIILjava/security/ProtectionDomain;)Ljava/lang/Class;
const #149 = Asciz	Registering class ;
const #150 = NameAndType	#231:#232;//  put:(Ljava/lang/Object;Ljava/lang/Object;)Ljava/lang/Object;
const #151 = Asciz	Found class. Returning.;
const #152 = Asciz	java/lang/Exception;
const #153 = Asciz	Couldn't get the class ourselves!;
const #154 = Asciz	Getting the system class.;
const #155 = NameAndType	#233:#100;//  findSystemClass:(Ljava/lang/String;)Ljava/lang/Class;
const #156 = Asciz	Couldn't find. Returning null.;
const #157 = Asciz	java/io/File;
const #158 = NameAndType	#95:#221;//  "<init>":(Ljava/lang/String;)V
const #159 = NameAndType	#234:#235;//  length:()J
const #160 = Asciz	java/io/FileInputStream;
const #161 = NameAndType	#95:#236;//  "<init>":(Ljava/io/File;)V
const #162 = Asciz	java/io/DataInputStream;
const #163 = NameAndType	#95:#237;//  "<init>":(Ljava/io/InputStream;)V
const #164 = NameAndType	#238:#239;//  readFully:([B)V
const #165 = NameAndType	#240:#96;//  close:()V
const #166 = NameAndType	#93:#90;//  MethodNameComparator:Ljava/util/Comparator;
const #167 = class	#241;	//  java/util/Arrays
const #168 = NameAndType	#242:#243;//  sort:([Ljava/lang/Object;Ljava/util/Comparator;)V
const #169 = Asciz	\tMethod: ;
const #170 = class	#244;	//  java/lang/reflect/Method
const #171 = NameAndType	#245:#218;//  getName:()Ljava/lang/String;
const #172 = Asciz	There are ;
const #173 = NameAndType	#215:#246;//  append:(I)Ljava/lang/StringBuilder;
const #174 = Asciz	 interfaces!;
const #175 = NameAndType	#89:#90;//  ClassNameComparator:Ljava/util/Comparator;
const #176 = Asciz	Interface: ;
const #177 = NameAndType	#247:#248;//  getMethods:()[Ljava/lang/reflect/Method;
const #178 = NameAndType	#110:#111;//  printMethods:([Ljava/lang/reflect/Method;)V
const #179 = Asciz	classes/test/CustomClassLoader2$CustomException;
const #180 = Asciz	classes/test/CustomClassLoader2$CustomException2;
const #181 = Asciz	Loading Dog...;
const #182 = Asciz	classes.test.Dog;
const #183 = NameAndType	#99:#100;//  loadClass:(Ljava/lang/String;)Ljava/lang/Class;
const #184 = Asciz	Dog's methods;
const #185 = Asciz	Getting Dog's interfaces...;
const #186 = NameAndType	#249:#250;//  getInterfaces:()[Ljava/lang/Class;
const #187 = NameAndType	#113:#114;//  printInterfaces:([Ljava/lang/Class;)V
const #188 = Asciz	Now let's resolve dog...;
const #189 = NameAndType	#251:#252;//  resolveClass:(Ljava/lang/Class;)V
const #190 = NameAndType	#253:#254;//  getSuperclass:()Ljava/lang/Class;
const #191 = Asciz	Super class: ;
const #192 = Asciz	classes.test.CatchBootstrapExceptions;
const #193 = Asciz	catcher;
const #194 = Asciz	java/lang/Character;
const #195 = NameAndType	#255:#256;//  getMethod:(Ljava/lang/String;[Ljava/lang/Class;)Ljava/lang/reflect/Method;
const #196 = Asciz	Obtained catcher Method.;
const #197 = NameAndType	#257:#258;//  setAccessible:(Z)V
const #198 = Asciz	java/lang/Object;
const #199 = NameAndType	#259:#260;//  valueOf:(C)Ljava/lang/Character;
const #200 = NameAndType	#261:#262;//  invoke:(Ljava/lang/Object;[Ljava/lang/Object;)Ljava/lang/Object;
const #201 = Asciz	classes/test/CustomClassLoader2$1;
const #202 = Asciz	;
const #203 = Asciz	classes/test/CustomClassLoader2$2;
const #204 = Asciz	java/lang/ClassLoader;
const #205 = Asciz	java/lang/ClassNotFoundException;
const #206 = Asciz	java/io/IOException;
const #207 = Asciz	[Ljava/lang/reflect/Method;;
const #208 = Asciz	[Ljava/lang/Class;;
const #209 = Asciz	getClassLoader;
const #210 = Asciz	()Ljava/lang/ClassLoader;;
const #211 = Asciz	(Ljava/lang/ClassLoader;)V;
const #212 = Asciz	java/lang/System;
const #213 = Asciz	out;
const #214 = Asciz	Ljava/io/PrintStream;;
const #215 = Asciz	append;
const #216 = Asciz	(Ljava/lang/String;)Ljava/lang/StringBuilder;;
const #217 = Asciz	toString;
const #218 = Asciz	()Ljava/lang/String;;
const #219 = Asciz	java/io/PrintStream;
const #220 = Asciz	println;
const #221 = Asciz	(Ljava/lang/String;)V;
const #222 = Asciz	get;
const #223 = Asciz	(Ljava/lang/Object;)Ljava/lang/Object;;
const #224 = Asciz	separatorChar;
const #225 = Asciz	C;
const #226 = Asciz	java/lang/String;
const #227 = Asciz	replace;
const #228 = Asciz	(CC)Ljava/lang/String;;
const #229 = Asciz	defineClass;
const #230 = Asciz	(Ljava/lang/String;[BIILjava/security/ProtectionDomain;)Ljava/lang/Class;;
const #231 = Asciz	put;
const #232 = Asciz	(Ljava/lang/Object;Ljava/lang/Object;)Ljava/lang/Object;;
const #233 = Asciz	findSystemClass;
const #234 = Asciz	length;
const #235 = Asciz	()J;
const #236 = Asciz	(Ljava/io/File;)V;
const #237 = Asciz	(Ljava/io/InputStream;)V;
const #238 = Asciz	readFully;
const #239 = Asciz	([B)V;
const #240 = Asciz	close;
const #241 = Asciz	java/util/Arrays;
const #242 = Asciz	sort;
const #243 = Asciz	([Ljava/lang/Object;Ljava/util/Comparator;)V;
const #244 = Asciz	java/lang/reflect/Method;
const #245 = Asciz	getName;
const #246 = Asciz	(I)Ljava/lang/StringBuilder;;
const #247 = Asciz	getMethods;
const #248 = Asciz	()[Ljava/lang/reflect/Method;;
const #249 = Asciz	getInterfaces;
const #250 = Asciz	()[Ljava/lang/Class;;
const #251 = Asciz	resolveClass;
const #252 = Asciz	(Ljava/lang/Class;)V;
const #253 = Asciz	getSuperclass;
const #254 = Asciz	()Ljava/lang/Class;;
const #255 = Asciz	getMethod;
const #256 = Asciz	(Ljava/lang/String;[Ljava/lang/Class;)Ljava/lang/reflect/Method;;
const #257 = Asciz	setAccessible;
const #258 = Asciz	(Z)V;
const #259 = Asciz	valueOf;
const #260 = Asciz	(C)Ljava/lang/Character;;
const #261 = Asciz	invoke;
const #262 = Asciz	(Ljava/lang/Object;[Ljava/lang/Object;)Ljava/lang/Object;;

{
private java.util.Hashtable classes;


public static java.util.Comparator ClassNameComparator;
  Signature: length = 0x2
   00 5C 


public static java.util.Comparator MethodNameComparator;
  Signature: length = 0x2
   00 5E 


public classes.test.CustomClassLoader2();
  Code:
   Stack=3, Locals=1, Args_size=1
   0:	aload_0
   1:	ldc_w	#1; //class classes/test/CustomClassLoader2
   4:	invokevirtual	#2; //Method java/lang/Class.getClassLoader:()Ljava/lang/ClassLoader;
   7:	invokespecial	#3; //Method java/lang/ClassLoader."<init>":(Ljava/lang/ClassLoader;)V
   10:	aload_0
   11:	new	#4; //class java/util/Hashtable
   14:	dup
   15:	invokespecial	#5; //Method java/util/Hashtable."<init>":()V
   18:	putfield	#6; //Field classes:Ljava/util/Hashtable;
   21:	return
  LineNumberTable: 
   line 18: 0
   line 15: 10
   line 19: 21


public java.lang.Class loadClass(java.lang.String)   throws java.lang.ClassNotFoundException;
  Code:
   Stack=3, Locals=2, Args_size=2
   0:	getstatic	#7; //Field java/lang/System.out:Ljava/io/PrintStream;
   3:	new	#8; //class java/lang/StringBuilder
   6:	dup
   7:	invokespecial	#9; //Method java/lang/StringBuilder."<init>":()V
   10:	ldc	#10; //String Loading class 
   12:	invokevirtual	#11; //Method java/lang/StringBuilder.append:(Ljava/lang/String;)Ljava/lang/StringBuilder;
   15:	aload_1
   16:	invokevirtual	#11; //Method java/lang/StringBuilder.append:(Ljava/lang/String;)Ljava/lang/StringBuilder;
   19:	invokevirtual	#12; //Method java/lang/StringBuilder.toString:()Ljava/lang/String;
   22:	invokevirtual	#13; //Method java/io/PrintStream.println:(Ljava/lang/String;)V
   25:	aload_0
   26:	aload_1
   27:	invokevirtual	#14; //Method findClass:(Ljava/lang/String;)Ljava/lang/Class;
   30:	areturn
  LineNumberTable: 
   line 46: 0
   line 47: 25

  Exceptions: 
   throws java.lang.ClassNotFoundException
public java.lang.Class findClass(java.lang.String);
  Code:
   Stack=6, Locals=5, Args_size=2
   0:	getstatic	#7; //Field java/lang/System.out:Ljava/io/PrintStream;
   3:	new	#8; //class java/lang/StringBuilder
   6:	dup
   7:	invokespecial	#9; //Method java/lang/StringBuilder."<init>":()V
   10:	ldc	#15; //String Finding class 
   12:	invokevirtual	#11; //Method java/lang/StringBuilder.append:(Ljava/lang/String;)Ljava/lang/StringBuilder;
   15:	aload_1
   16:	invokevirtual	#11; //Method java/lang/StringBuilder.append:(Ljava/lang/String;)Ljava/lang/StringBuilder;
   19:	invokevirtual	#12; //Method java/lang/StringBuilder.toString:()Ljava/lang/String;
   22:	invokevirtual	#13; //Method java/io/PrintStream.println:(Ljava/lang/String;)V
   25:	aconst_null
   26:	astore_3
   27:	aload_0
   28:	getfield	#6; //Field classes:Ljava/util/Hashtable;
   31:	aload_1
   32:	invokevirtual	#16; //Method java/util/Hashtable.get:(Ljava/lang/Object;)Ljava/lang/Object;
   35:	checkcast	#17; //class java/lang/Class
   38:	astore_3
   39:	aload_3
   40:	ifnull	45
   43:	aload_3
   44:	areturn
   45:	aload_0
   46:	new	#8; //class java/lang/StringBuilder
   49:	dup
   50:	invokespecial	#9; //Method java/lang/StringBuilder."<init>":()V
   53:	ldc	#18; //String classes/test/data/CustomClassLoader2/
   55:	invokevirtual	#11; //Method java/lang/StringBuilder.append:(Ljava/lang/String;)Ljava/lang/StringBuilder;
   58:	aload_1
   59:	bipush	46
   61:	getstatic	#19; //Field java/io/File.separatorChar:C
   64:	invokevirtual	#20; //Method java/lang/String.replace:(CC)Ljava/lang/String;
   67:	invokevirtual	#11; //Method java/lang/StringBuilder.append:(Ljava/lang/String;)Ljava/lang/StringBuilder;
   70:	ldc	#21; //String .class
   72:	invokevirtual	#11; //Method java/lang/StringBuilder.append:(Ljava/lang/String;)Ljava/lang/StringBuilder;
   75:	invokevirtual	#12; //Method java/lang/StringBuilder.toString:()Ljava/lang/String;
   78:	invokespecial	#22; //Method loadClassData:(Ljava/lang/String;)[B
   81:	astore_2
   82:	getstatic	#7; //Field java/lang/System.out:Ljava/io/PrintStream;
   85:	new	#8; //class java/lang/StringBuilder
   88:	dup
   89:	invokespecial	#9; //Method java/lang/StringBuilder."<init>":()V
   92:	ldc	#23; //String Defining class 
   94:	invokevirtual	#11; //Method java/lang/StringBuilder.append:(Ljava/lang/String;)Ljava/lang/StringBuilder;
   97:	aload_1
   98:	invokevirtual	#11; //Method java/lang/StringBuilder.append:(Ljava/lang/String;)Ljava/lang/StringBuilder;
   101:	invokevirtual	#12; //Method java/lang/StringBuilder.toString:()Ljava/lang/String;
   104:	invokevirtual	#13; //Method java/io/PrintStream.println:(Ljava/lang/String;)V
   107:	aload_0
   108:	aload_1
   109:	aload_2
   110:	iconst_0
   111:	aload_2
   112:	arraylength
   113:	aconst_null
   114:	invokevirtual	#24; //Method defineClass:(Ljava/lang/String;[BIILjava/security/ProtectionDomain;)Ljava/lang/Class;
   117:	astore_3
   118:	getstatic	#7; //Field java/lang/System.out:Ljava/io/PrintStream;
   121:	new	#8; //class java/lang/StringBuilder
   124:	dup
   125:	invokespecial	#9; //Method java/lang/StringBuilder."<init>":()V
   128:	ldc	#25; //String Registering class 
   130:	invokevirtual	#11; //Method java/lang/StringBuilder.append:(Ljava/lang/String;)Ljava/lang/StringBuilder;
   133:	aload_1
   134:	invokevirtual	#11; //Method java/lang/StringBuilder.append:(Ljava/lang/String;)Ljava/lang/StringBuilder;
   137:	invokevirtual	#12; //Method java/lang/StringBuilder.toString:()Ljava/lang/String;
   140:	invokevirtual	#13; //Method java/io/PrintStream.println:(Ljava/lang/String;)V
   143:	aload_0
   144:	getfield	#6; //Field classes:Ljava/util/Hashtable;
   147:	aload_1
   148:	aload_3
   149:	invokevirtual	#26; //Method java/util/Hashtable.put:(Ljava/lang/Object;Ljava/lang/Object;)Ljava/lang/Object;
   152:	pop
   153:	getstatic	#7; //Field java/lang/System.out:Ljava/io/PrintStream;
   156:	ldc	#27; //String Found class. Returning.
   158:	invokevirtual	#13; //Method java/io/PrintStream.println:(Ljava/lang/String;)V
   161:	aload_3
   162:	areturn
   163:	astore	4
   165:	getstatic	#7; //Field java/lang/System.out:Ljava/io/PrintStream;
   168:	ldc	#29; //String Couldn't get the class ourselves!
   170:	invokevirtual	#13; //Method java/io/PrintStream.println:(Ljava/lang/String;)V
   173:	getstatic	#7; //Field java/lang/System.out:Ljava/io/PrintStream;
   176:	ldc	#30; //String Getting the system class.
   178:	invokevirtual	#13; //Method java/io/PrintStream.println:(Ljava/lang/String;)V
   181:	aload_0
   182:	aload_1
   183:	invokevirtual	#31; //Method findSystemClass:(Ljava/lang/String;)Ljava/lang/Class;
   186:	areturn
   187:	astore	4
   189:	getstatic	#7; //Field java/lang/System.out:Ljava/io/PrintStream;
   192:	ldc	#32; //String Couldn't find. Returning null.
   194:	invokevirtual	#13; //Method java/io/PrintStream.println:(Ljava/lang/String;)V
   197:	aconst_null
   198:	areturn
  Exception table:
   from   to  target type
    45   162   163   Class java/lang/Exception

   173   186   187   Class java/lang/Exception

  LineNumberTable: 
   line 51: 0
   line 53: 25
   line 54: 27
   line 55: 39
   line 56: 43
   line 61: 45
   line 62: 82
   line 63: 107
   line 64: 118
   line 65: 143
   line 66: 153
   line 67: 161
   line 68: 163
   line 69: 165
   line 73: 173
   line 74: 181
   line 75: 187
   line 76: 189
   line 77: 197

  StackMapTable: number_of_entries = 3
   frame_type = 253 /* append */
     offset_delta = 45
     locals = [ bogus, class java/lang/Class ]
   frame_type = 247 /* same_locals_1_stack_item_frame_extended */
     offset_delta = 117
     stack = [ class java/lang/Exception ]
   frame_type = 87 /* same_locals_1_stack_item */
     stack = [ class java/lang/Exception ]


private byte[] loadClassData(java.lang.String)   throws java.io.IOException;
  Code:
   Stack=3, Locals=7, Args_size=2
   0:	new	#33; //class java/io/File
   3:	dup
   4:	aload_1
   5:	invokespecial	#34; //Method java/io/File."<init>":(Ljava/lang/String;)V
   8:	astore_2
   9:	aload_2
   10:	invokevirtual	#35; //Method java/io/File.length:()J
   13:	l2i
   14:	istore_3
   15:	iload_3
   16:	newarray byte
   18:	astore	4
   20:	new	#36; //class java/io/FileInputStream
   23:	dup
   24:	aload_2
   25:	invokespecial	#37; //Method java/io/FileInputStream."<init>":(Ljava/io/File;)V
   28:	astore	5
   30:	new	#38; //class java/io/DataInputStream
   33:	dup
   34:	aload	5
   36:	invokespecial	#39; //Method java/io/DataInputStream."<init>":(Ljava/io/InputStream;)V
   39:	astore	6
   41:	aload	6
   43:	aload	4
   45:	invokevirtual	#40; //Method java/io/DataInputStream.readFully:([B)V
   48:	aload	6
   50:	invokevirtual	#41; //Method java/io/DataInputStream.close:()V
   53:	aload	4
   55:	areturn
  LineNumberTable: 
   line 83: 0
   line 84: 9
   line 85: 15
   line 86: 20
   line 87: 30
   line 88: 41
   line 89: 48
   line 90: 53

  Exceptions: 
   throws java.io.IOException
public static void printMethods(java.lang.reflect.Method[]);
  Code:
   Stack=3, Locals=5, Args_size=1
   0:	aload_0
   1:	getstatic	#42; //Field MethodNameComparator:Ljava/util/Comparator;
   4:	invokestatic	#43; //Method java/util/Arrays.sort:([Ljava/lang/Object;Ljava/util/Comparator;)V
   7:	aload_0
   8:	astore_1
   9:	aload_1
   10:	arraylength
   11:	istore_2
   12:	iconst_0
   13:	istore_3
   14:	iload_3
   15:	iload_2
   16:	if_icmpge	59
   19:	aload_1
   20:	iload_3
   21:	aaload
   22:	astore	4
   24:	getstatic	#7; //Field java/lang/System.out:Ljava/io/PrintStream;
   27:	new	#8; //class java/lang/StringBuilder
   30:	dup
   31:	invokespecial	#9; //Method java/lang/StringBuilder."<init>":()V
   34:	ldc	#44; //String \tMethod: 
   36:	invokevirtual	#11; //Method java/lang/StringBuilder.append:(Ljava/lang/String;)Ljava/lang/StringBuilder;
   39:	aload	4
   41:	invokevirtual	#45; //Method java/lang/reflect/Method.getName:()Ljava/lang/String;
   44:	invokevirtual	#11; //Method java/lang/StringBuilder.append:(Ljava/lang/String;)Ljava/lang/StringBuilder;
   47:	invokevirtual	#12; //Method java/lang/StringBuilder.toString:()Ljava/lang/String;
   50:	invokevirtual	#13; //Method java/io/PrintStream.println:(Ljava/lang/String;)V
   53:	iinc	3, 1
   56:	goto	14
   59:	return
  LineNumberTable: 
   line 94: 0
   line 95: 7
   line 96: 24
   line 95: 53
   line 97: 59

  StackMapTable: number_of_entries = 2
   frame_type = 254 /* append */
     offset_delta = 14
     locals = [ class "[Ljava/lang/reflect/Method;", int, int ]
   frame_type = 248 /* chop */
     offset_delta = 44


public static void printInterfaces(java.lang.Class[]);
  Code:
   Stack=3, Locals=5, Args_size=1
   0:	getstatic	#7; //Field java/lang/System.out:Ljava/io/PrintStream;
   3:	new	#8; //class java/lang/StringBuilder
   6:	dup
   7:	invokespecial	#9; //Method java/lang/StringBuilder."<init>":()V
   10:	ldc	#46; //String There are 
   12:	invokevirtual	#11; //Method java/lang/StringBuilder.append:(Ljava/lang/String;)Ljava/lang/StringBuilder;
   15:	aload_0
   16:	arraylength
   17:	invokevirtual	#47; //Method java/lang/StringBuilder.append:(I)Ljava/lang/StringBuilder;
   20:	ldc	#48; //String  interfaces!
   22:	invokevirtual	#11; //Method java/lang/StringBuilder.append:(Ljava/lang/String;)Ljava/lang/StringBuilder;
   25:	invokevirtual	#12; //Method java/lang/StringBuilder.toString:()Ljava/lang/String;
   28:	invokevirtual	#13; //Method java/io/PrintStream.println:(Ljava/lang/String;)V
   31:	aload_0
   32:	getstatic	#49; //Field ClassNameComparator:Ljava/util/Comparator;
   35:	invokestatic	#43; //Method java/util/Arrays.sort:([Ljava/lang/Object;Ljava/util/Comparator;)V
   38:	aload_0
   39:	astore_1
   40:	aload_1
   41:	arraylength
   42:	istore_2
   43:	iconst_0
   44:	istore_3
   45:	iload_3
   46:	iload_2
   47:	if_icmpge	98
   50:	aload_1
   51:	iload_3
   52:	aaload
   53:	astore	4
   55:	getstatic	#7; //Field java/lang/System.out:Ljava/io/PrintStream;
   58:	new	#8; //class java/lang/StringBuilder
   61:	dup
   62:	invokespecial	#9; //Method java/lang/StringBuilder."<init>":()V
   65:	ldc	#50; //String Interface: 
   67:	invokevirtual	#11; //Method java/lang/StringBuilder.append:(Ljava/lang/String;)Ljava/lang/StringBuilder;
   70:	aload	4
   72:	invokevirtual	#51; //Method java/lang/Class.getName:()Ljava/lang/String;
   75:	invokevirtual	#11; //Method java/lang/StringBuilder.append:(Ljava/lang/String;)Ljava/lang/StringBuilder;
   78:	invokevirtual	#12; //Method java/lang/StringBuilder.toString:()Ljava/lang/String;
   81:	invokevirtual	#13; //Method java/io/PrintStream.println:(Ljava/lang/String;)V
   84:	aload	4
   86:	invokevirtual	#52; //Method java/lang/Class.getMethods:()[Ljava/lang/reflect/Method;
   89:	invokestatic	#53; //Method printMethods:([Ljava/lang/reflect/Method;)V
   92:	iinc	3, 1
   95:	goto	45
   98:	return
  LineNumberTable: 
   line 100: 0
   line 101: 31
   line 102: 38
   line 103: 55
   line 104: 84
   line 102: 92
   line 106: 98

  StackMapTable: number_of_entries = 2
   frame_type = 254 /* append */
     offset_delta = 45
     locals = [ class "[Ljava/lang/Class;", int, int ]
   frame_type = 248 /* chop */
     offset_delta = 52


public static void throwBootstrapException()   throws classes.test.CustomClassLoader2$CustomException;
  Code:
   Stack=2, Locals=0, Args_size=0
   0:	new	#54; //class classes/test/CustomClassLoader2$CustomException
   3:	dup
   4:	invokespecial	#55; //Method classes/test/CustomClassLoader2$CustomException."<init>":()V
   7:	athrow
  LineNumberTable: 
   line 109: 0

  Exceptions: 
   throws classes.test.CustomClassLoader2$CustomException
public static void throwBootstrapException2()   throws classes.test.CustomClassLoader2$CustomException2;
  Code:
   Stack=2, Locals=0, Args_size=0
   0:	new	#56; //class classes/test/CustomClassLoader2$CustomException2
   3:	dup
   4:	invokespecial	#57; //Method classes/test/CustomClassLoader2$CustomException2."<init>":()V
   7:	athrow
  LineNumberTable: 
   line 113: 0

  Exceptions: 
   throws classes.test.CustomClassLoader2$CustomException2
public static void main(java.lang.String[])   throws java.lang.Exception;
  Code:
   Stack=6, Locals=6, Args_size=1
   0:	new	#1; //class classes/test/CustomClassLoader2
   3:	dup
   4:	invokespecial	#58; //Method "<init>":()V
   7:	astore_1
   8:	getstatic	#7; //Field java/lang/System.out:Ljava/io/PrintStream;
   11:	ldc	#59; //String Loading Dog...
   13:	invokevirtual	#13; //Method java/io/PrintStream.println:(Ljava/lang/String;)V
   16:	aload_1
   17:	ldc	#60; //String classes.test.Dog
   19:	invokevirtual	#61; //Method loadClass:(Ljava/lang/String;)Ljava/lang/Class;
   22:	astore_2
   23:	getstatic	#7; //Field java/lang/System.out:Ljava/io/PrintStream;
   26:	ldc	#62; //String Dog's methods
   28:	invokevirtual	#13; //Method java/io/PrintStream.println:(Ljava/lang/String;)V
   31:	aload_2
   32:	invokevirtual	#52; //Method java/lang/Class.getMethods:()[Ljava/lang/reflect/Method;
   35:	invokestatic	#53; //Method printMethods:([Ljava/lang/reflect/Method;)V
   38:	getstatic	#7; //Field java/lang/System.out:Ljava/io/PrintStream;
   41:	ldc	#63; //String Getting Dog's interfaces...
   43:	invokevirtual	#13; //Method java/io/PrintStream.println:(Ljava/lang/String;)V
   46:	aload_2
   47:	invokevirtual	#64; //Method java/lang/Class.getInterfaces:()[Ljava/lang/Class;
   50:	invokestatic	#65; //Method printInterfaces:([Ljava/lang/Class;)V
   53:	getstatic	#7; //Field java/lang/System.out:Ljava/io/PrintStream;
   56:	ldc	#66; //String Now let's resolve dog...
   58:	invokevirtual	#13; //Method java/io/PrintStream.println:(Ljava/lang/String;)V
   61:	aload_1
   62:	aload_2
   63:	invokevirtual	#67; //Method resolveClass:(Ljava/lang/Class;)V
   66:	aload_2
   67:	invokevirtual	#64; //Method java/lang/Class.getInterfaces:()[Ljava/lang/Class;
   70:	invokestatic	#65; //Method printInterfaces:([Ljava/lang/Class;)V
   73:	aload_2
   74:	invokevirtual	#68; //Method java/lang/Class.getSuperclass:()Ljava/lang/Class;
   77:	astore_3
   78:	getstatic	#7; //Field java/lang/System.out:Ljava/io/PrintStream;
   81:	new	#8; //class java/lang/StringBuilder
   84:	dup
   85:	invokespecial	#9; //Method java/lang/StringBuilder."<init>":()V
   88:	ldc	#69; //String Super class: 
   90:	invokevirtual	#11; //Method java/lang/StringBuilder.append:(Ljava/lang/String;)Ljava/lang/StringBuilder;
   93:	aload_3
   94:	invokevirtual	#51; //Method java/lang/Class.getName:()Ljava/lang/String;
   97:	invokevirtual	#11; //Method java/lang/StringBuilder.append:(Ljava/lang/String;)Ljava/lang/StringBuilder;
   100:	invokevirtual	#12; //Method java/lang/StringBuilder.toString:()Ljava/lang/String;
   103:	invokevirtual	#13; //Method java/io/PrintStream.println:(Ljava/lang/String;)V
   106:	aload_3
   107:	invokevirtual	#52; //Method java/lang/Class.getMethods:()[Ljava/lang/reflect/Method;
   110:	invokestatic	#53; //Method printMethods:([Ljava/lang/reflect/Method;)V
   113:	aload_1
   114:	ldc	#70; //String classes.test.CatchBootstrapExceptions
   116:	invokevirtual	#61; //Method loadClass:(Ljava/lang/String;)Ljava/lang/Class;
   119:	astore	4
   121:	aload	4
   123:	ldc	#71; //String catcher
   125:	iconst_1
   126:	anewarray	#17; //class java/lang/Class
   129:	dup
   130:	iconst_0
   131:	ldc_w	#72; //class java/lang/Character
   134:	aastore
   135:	invokevirtual	#73; //Method java/lang/Class.getMethod:(Ljava/lang/String;[Ljava/lang/Class;)Ljava/lang/reflect/Method;
   138:	astore	5
   140:	getstatic	#7; //Field java/lang/System.out:Ljava/io/PrintStream;
   143:	ldc	#74; //String Obtained catcher Method.
   145:	invokevirtual	#13; //Method java/io/PrintStream.println:(Ljava/lang/String;)V
   148:	aload	5
   150:	iconst_1
   151:	invokevirtual	#75; //Method java/lang/reflect/Method.setAccessible:(Z)V
   154:	aload	5
   156:	aconst_null
   157:	iconst_1
   158:	anewarray	#76; //class java/lang/Object
   161:	dup
   162:	iconst_0
   163:	bipush	97
   165:	invokestatic	#77; //Method java/lang/Character.valueOf:(C)Ljava/lang/Character;
   168:	aastore
   169:	invokevirtual	#78; //Method java/lang/reflect/Method.invoke:(Ljava/lang/Object;[Ljava/lang/Object;)Ljava/lang/Object;
   172:	pop
   173:	return
  LineNumberTable: 
   line 119: 0
   line 120: 8
   line 121: 16
   line 123: 23
   line 124: 31
   line 126: 38
   line 127: 46
   line 129: 53
   line 130: 61
   line 131: 66
   line 133: 73
   line 134: 78
   line 135: 106
   line 137: 113
   line 138: 121
   line 139: 140
   line 143: 148
   line 144: 154
   line 145: 173

  Exceptions: 
   throws java.lang.Exception
static {};
  Code:
   Stack=2, Locals=0, Args_size=0
   0:	new	#79; //class classes/test/CustomClassLoader2$1
   3:	dup
   4:	invokespecial	#80; //Method classes/test/CustomClassLoader2$1."<init>":()V
   7:	putstatic	#49; //Field ClassNameComparator:Ljava/util/Comparator;
   10:	new	#81; //class classes/test/CustomClassLoader2$2
   13:	dup
   14:	invokespecial	#82; //Method classes/test/CustomClassLoader2$2."<init>":()V
   17:	putstatic	#42; //Field MethodNameComparator:Ljava/util/Comparator;
   20:	return
  LineNumberTable: 
   line 21: 0
   line 29: 10


}

