Compiled from "Exceptional.java"
public class classes.test.Exceptional extends java.lang.Object
  SourceFile: "Exceptional.java"
  minor version: 0
  major version: 50
  Constant pool:
const #1 = Method	#37.#56;	//  java/lang/Object."<init>":()V
const #2 = class	#57;	//  java/lang/Exception
const #3 = String	#58;	//  good morning
const #4 = Method	#2.#59;	//  java/lang/Exception."<init>":(Ljava/lang/String;)V
const #5 = class	#60;	//  java/lang/RuntimeException
const #6 = String	#61;	//  bad morning
const #7 = Method	#5.#59;	//  java/lang/RuntimeException."<init>":(Ljava/lang/String;)V
const #8 = Field	#62.#63;	//  java/lang/System.out:Ljava/io/PrintStream;
const #9 = String	#64;	//  Caught RuntimeException as a subclass of Exception.
const #10 = Method	#65.#66;	//  java/io/PrintStream.println:(Ljava/lang/String;)V
const #11 = String	#67;	//  test
const #12 = Method	#36.#68;	//  classes/test/Exceptional.throwingFunc:()V
const #13 = Method	#36.#69;	//  classes/test/Exceptional.anotherThrowingFunc:()V
const #14 = class	#70;	//  java/io/FileReader
const #15 = String	#71;	//  ./NonExistentFile!!!
const #16 = Method	#14.#59;	//  java/io/FileReader."<init>":(Ljava/lang/String;)V
const #17 = Method	#2.#72;	//  java/lang/Exception.getMessage:()Ljava/lang/String;
const #18 = class	#73;	//  java/lang/StringBuilder
const #19 = Method	#18.#56;	//  java/lang/StringBuilder."<init>":()V
const #20 = String	#74;	//  trace depth: 
const #21 = Method	#18.#75;	//  java/lang/StringBuilder.append:(Ljava/lang/String;)Ljava/lang/StringBuilder;
const #22 = Method	#2.#76;	//  java/lang/Exception.getStackTrace:()[Ljava/lang/StackTraceElement;
const #23 = Method	#18.#77;	//  java/lang/StringBuilder.append:(I)Ljava/lang/StringBuilder;
const #24 = Method	#18.#78;	//  java/lang/StringBuilder.toString:()Ljava/lang/String;
const #25 = Method	#36.#79;	//  classes/test/Exceptional.notImplementedNative:()J
const #26 = class	#80;	//  java/lang/UnsatisfiedLinkError
const #27 = String	#81;	//  got an UnsatisfiedLinkError for a NYI native
const #28 = String	#82;	//  cowsay
const #29 = Method	#62.#83;	//  java/lang/System.loadLibrary:(Ljava/lang/String;)V
const #30 = Field	#62.#84;	//  java/lang/System.err:Ljava/io/PrintStream;
const #31 = Method	#26.#72;	//  java/lang/UnsatisfiedLinkError.getMessage:()Ljava/lang/String;
const #32 = class	#85;	//  java/lang/Error
const #33 = String	#86;	//  I'm the gingerbread man
const #34 = Method	#32.#59;	//  java/lang/Error."<init>":(Ljava/lang/String;)V
const #35 = String	#87;	//  We should never reach this -- Error is not a subclass of Exception
const #36 = class	#88;	//  classes/test/Exceptional
const #37 = class	#89;	//  java/lang/Object
const #38 = Asciz	<init>;
const #39 = Asciz	()V;
const #40 = Asciz	Code;
const #41 = Asciz	LineNumberTable;
const #42 = Asciz	notImplementedNative;
const #43 = Asciz	()J;
const #44 = Asciz	throwingFunc;
const #45 = Asciz	Exceptions;
const #46 = Asciz	anotherThrowingFunc;
const #47 = Asciz	StackMapTable;
const #48 = class	#57;	//  java/lang/Exception
const #49 = Asciz	main;
const #50 = Asciz	([Ljava/lang/String;)V;
const #51 = class	#90;	//  "[Ljava/lang/String;"
const #52 = class	#91;	//  java/lang/Throwable
const #53 = class	#80;	//  java/lang/UnsatisfiedLinkError
const #54 = Asciz	SourceFile;
const #55 = Asciz	Exceptional.java;
const #56 = NameAndType	#38:#39;//  "<init>":()V
const #57 = Asciz	java/lang/Exception;
const #58 = Asciz	good morning;
const #59 = NameAndType	#38:#92;//  "<init>":(Ljava/lang/String;)V
const #60 = Asciz	java/lang/RuntimeException;
const #61 = Asciz	bad morning;
const #62 = class	#93;	//  java/lang/System
const #63 = NameAndType	#94:#95;//  out:Ljava/io/PrintStream;
const #64 = Asciz	Caught RuntimeException as a subclass of Exception.;
const #65 = class	#96;	//  java/io/PrintStream
const #66 = NameAndType	#97:#92;//  println:(Ljava/lang/String;)V
const #67 = Asciz	test;
const #68 = NameAndType	#44:#39;//  throwingFunc:()V
const #69 = NameAndType	#46:#39;//  anotherThrowingFunc:()V
const #70 = Asciz	java/io/FileReader;
const #71 = Asciz	./NonExistentFile!!!;
const #72 = NameAndType	#98:#99;//  getMessage:()Ljava/lang/String;
const #73 = Asciz	java/lang/StringBuilder;
const #74 = Asciz	trace depth: ;
const #75 = NameAndType	#100:#101;//  append:(Ljava/lang/String;)Ljava/lang/StringBuilder;
const #76 = NameAndType	#102:#103;//  getStackTrace:()[Ljava/lang/StackTraceElement;
const #77 = NameAndType	#100:#104;//  append:(I)Ljava/lang/StringBuilder;
const #78 = NameAndType	#105:#99;//  toString:()Ljava/lang/String;
const #79 = NameAndType	#42:#43;//  notImplementedNative:()J
const #80 = Asciz	java/lang/UnsatisfiedLinkError;
const #81 = Asciz	got an UnsatisfiedLinkError for a NYI native;
const #82 = Asciz	cowsay;
const #83 = NameAndType	#106:#92;//  loadLibrary:(Ljava/lang/String;)V
const #84 = NameAndType	#107:#95;//  err:Ljava/io/PrintStream;
const #85 = Asciz	java/lang/Error;
const #86 = Asciz	I'm the gingerbread man;
const #87 = Asciz	We should never reach this -- Error is not a subclass of Exception;
const #88 = Asciz	classes/test/Exceptional;
const #89 = Asciz	java/lang/Object;
const #90 = Asciz	[Ljava/lang/String;;
const #91 = Asciz	java/lang/Throwable;
const #92 = Asciz	(Ljava/lang/String;)V;
const #93 = Asciz	java/lang/System;
const #94 = Asciz	out;
const #95 = Asciz	Ljava/io/PrintStream;;
const #96 = Asciz	java/io/PrintStream;
const #97 = Asciz	println;
const #98 = Asciz	getMessage;
const #99 = Asciz	()Ljava/lang/String;;
const #100 = Asciz	append;
const #101 = Asciz	(Ljava/lang/String;)Ljava/lang/StringBuilder;;
const #102 = Asciz	getStackTrace;
const #103 = Asciz	()[Ljava/lang/StackTraceElement;;
const #104 = Asciz	(I)Ljava/lang/StringBuilder;;
const #105 = Asciz	toString;
const #106 = Asciz	loadLibrary;
const #107 = Asciz	err;

{
public classes.test.Exceptional();
  Code:
   Stack=1, Locals=1, Args_size=1
   0:	aload_0
   1:	invokespecial	#1; //Method java/lang/Object."<init>":()V
   4:	return
  LineNumberTable: 
   line 5: 0


public static final native long notImplementedNative();

public static void throwingFunc()   throws java.lang.Exception;
  Code:
   Stack=3, Locals=1, Args_size=0
   0:	iconst_0
   1:	istore_0
   2:	new	#2; //class java/lang/Exception
   5:	dup
   6:	ldc	#3; //String good morning
   8:	invokespecial	#4; //Method java/lang/Exception."<init>":(Ljava/lang/String;)V
   11:	athrow
  LineNumberTable: 
   line 8: 0
   line 9: 2

  Exceptions: 
   throws java.lang.Exception
public static void anotherThrowingFunc();
  Code:
   Stack=3, Locals=1, Args_size=0
   0:	new	#5; //class java/lang/RuntimeException
   3:	dup
   4:	ldc	#6; //String bad morning
   6:	invokespecial	#7; //Method java/lang/RuntimeException."<init>":(Ljava/lang/String;)V
   9:	athrow
   10:	astore_0
   11:	getstatic	#8; //Field java/lang/System.out:Ljava/io/PrintStream;
   14:	ldc	#9; //String Caught RuntimeException as a subclass of Exception.
   16:	invokevirtual	#10; //Method java/io/PrintStream.println:(Ljava/lang/String;)V
   19:	return
  Exception table:
   from   to  target type
     0    10    10   Class java/lang/Exception

  LineNumberTable: 
   line 13: 0
   line 15: 10
   line 16: 11
   line 18: 19

  StackMapTable: number_of_entries = 1
   frame_type = 74 /* same_locals_1_stack_item */
     stack = [ class java/lang/Exception ]


public static void main(java.lang.String[]);
  Code:
   Stack=3, Locals=4, Args_size=1
   0:	new	#2; //class java/lang/Exception
   3:	dup
   4:	ldc	#11; //String test
   6:	invokespecial	#4; //Method java/lang/Exception."<init>":(Ljava/lang/String;)V
   9:	athrow
   10:	astore_1
   11:	iconst_1
   12:	istore_2
   13:	iconst_0
   14:	istore_1
   15:	invokestatic	#12; //Method throwingFunc:()V
   18:	goto	28
   21:	astore_2
   22:	iinc_w 1, 200
   28:	invokestatic	#13; //Method anotherThrowingFunc:()V
   31:	iinc_w 1, 1200
   37:	goto	65
   40:	astore_2
   41:	iinc_w 1, 900
   47:	iinc_w 1, 1200
   53:	goto	65
   56:	astore_3
   57:	iinc_w 1, 1200
   63:	aload_3
   64:	athrow
   65:	new	#14; //class java/io/FileReader
   68:	dup
   69:	ldc	#15; //String ./NonExistentFile!!!
   71:	invokespecial	#16; //Method java/io/FileReader."<init>":(Ljava/lang/String;)V
   74:	pop
   75:	goto	118
   78:	astore_2
   79:	getstatic	#8; //Field java/lang/System.out:Ljava/io/PrintStream;
   82:	aload_2
   83:	invokevirtual	#17; //Method java/lang/Exception.getMessage:()Ljava/lang/String;
   86:	invokevirtual	#10; //Method java/io/PrintStream.println:(Ljava/lang/String;)V
   89:	getstatic	#8; //Field java/lang/System.out:Ljava/io/PrintStream;
   92:	new	#18; //class java/lang/StringBuilder
   95:	dup
   96:	invokespecial	#19; //Method java/lang/StringBuilder."<init>":()V
   99:	ldc	#20; //String trace depth: 
   101:	invokevirtual	#21; //Method java/lang/StringBuilder.append:(Ljava/lang/String;)Ljava/lang/StringBuilder;
   104:	aload_2
   105:	invokevirtual	#22; //Method java/lang/Exception.getStackTrace:()[Ljava/lang/StackTraceElement;
   108:	arraylength
   109:	invokevirtual	#23; //Method java/lang/StringBuilder.append:(I)Ljava/lang/StringBuilder;
   112:	invokevirtual	#24; //Method java/lang/StringBuilder.toString:()Ljava/lang/String;
   115:	invokevirtual	#10; //Method java/io/PrintStream.println:(Ljava/lang/String;)V
   118:	invokestatic	#25; //Method notImplementedNative:()J
   121:	pop2
   122:	goto	134
   125:	astore_2
   126:	getstatic	#8; //Field java/lang/System.out:Ljava/io/PrintStream;
   129:	ldc	#27; //String got an UnsatisfiedLinkError for a NYI native
   131:	invokevirtual	#10; //Method java/io/PrintStream.println:(Ljava/lang/String;)V
   134:	ldc	#28; //String cowsay
   136:	invokestatic	#29; //Method java/lang/System.loadLibrary:(Ljava/lang/String;)V
   139:	goto	153
   142:	astore_2
   143:	getstatic	#30; //Field java/lang/System.err:Ljava/io/PrintStream;
   146:	aload_2
   147:	invokevirtual	#31; //Method java/lang/UnsatisfiedLinkError.getMessage:()Ljava/lang/String;
   150:	invokevirtual	#10; //Method java/io/PrintStream.println:(Ljava/lang/String;)V
   153:	new	#32; //class java/lang/Error
   156:	dup
   157:	ldc	#33; //String I'm the gingerbread man
   159:	invokespecial	#34; //Method java/lang/Error."<init>":(Ljava/lang/String;)V
   162:	athrow
   163:	astore_2
   164:	getstatic	#8; //Field java/lang/System.out:Ljava/io/PrintStream;
   167:	ldc	#35; //String We should never reach this -- Error is not a subclass of Exception
   169:	invokevirtual	#10; //Method java/io/PrintStream.println:(Ljava/lang/String;)V
   172:	return
  Exception table:
   from   to  target type
     0    10    10   Class java/lang/Exception

    15    18    21   Class java/lang/Exception

    28    31    40   Class java/lang/Exception

    28    31    56   any
    40    47    56   any
    56    57    56   any
    65    75    78   Class java/lang/Exception

   118   122   125   Class java/lang/UnsatisfiedLinkError

   134   139   142   Class java/lang/UnsatisfiedLinkError

   153   163   163   Class java/lang/Exception

  LineNumberTable: 
   line 21: 0
   line 22: 10
   line 23: 11
   line 26: 13
   line 28: 15
   line 31: 18
   line 29: 21
   line 30: 22
   line 34: 28
   line 40: 31
   line 41: 37
   line 36: 40
   line 37: 41
   line 40: 47
   line 41: 53
   line 40: 56
   line 45: 65
   line 50: 75
   line 47: 78
   line 48: 79
   line 49: 89
   line 54: 118
   line 58: 122
   line 55: 125
   line 57: 126
   line 62: 134
   line 65: 139
   line 63: 142
   line 64: 143
   line 68: 153
   line 70: 163
   line 71: 164
   line 73: 172

  StackMapTable: number_of_entries = 13
   frame_type = 74 /* same_locals_1_stack_item */
     stack = [ class java/lang/Exception ]
   frame_type = 255 /* full_frame */
     offset_delta = 10
     locals = [ class "[Ljava/lang/String;", int ]
     stack = [ class java/lang/Exception ]
   frame_type = 6 /* same */
   frame_type = 75 /* same_locals_1_stack_item */
     stack = [ class java/lang/Exception ]
   frame_type = 79 /* same_locals_1_stack_item */
     stack = [ class java/lang/Throwable ]
   frame_type = 8 /* same */
   frame_type = 76 /* same_locals_1_stack_item */
     stack = [ class java/lang/Exception ]
   frame_type = 39 /* same */
   frame_type = 70 /* same_locals_1_stack_item */
     stack = [ class java/lang/UnsatisfiedLinkError ]
   frame_type = 8 /* same */
   frame_type = 71 /* same_locals_1_stack_item */
     stack = [ class java/lang/UnsatisfiedLinkError ]
   frame_type = 10 /* same */
   frame_type = 73 /* same_locals_1_stack_item */
     stack = [ class java/lang/Exception ]


}

