Compiled from "PackageTest.java"
class classes.test.PackageTest extends java.lang.Object
  SourceFile: "PackageTest.java"
  minor version: 0
  major version: 50
  Constant pool:
const #1 = Method	#20.#34;	//  java/lang/Object."<init>":()V
const #2 = String	#35;	//  java.lang
const #3 = Method	#36.#37;	//  java/lang/Package.getPackage:(Ljava/lang/String;)Ljava/lang/Package;
const #4 = Field	#38.#39;	//  java/lang/System.out:Ljava/io/PrintStream;
const #5 = Method	#36.#40;	//  java/lang/Package.getName:()Ljava/lang/String;
const #6 = Method	#41.#42;	//  java/io/PrintStream.println:(Ljava/lang/String;)V
const #7 = Method	#36.#43;	//  java/lang/Package.getPackages:()[Ljava/lang/Package;
const #8 = class	#44;	//  java/util/HashSet
const #9 = Method	#8.#34;	//  java/util/HashSet."<init>":()V
const #10 = Method	#8.#45;	//  java/util/HashSet.add:(Ljava/lang/Object;)Z
const #11 = String	#46;	//  java.io
const #12 = String	#47;	//  java.util
const #13 = Method	#8.#48;	//  java/util/HashSet.contains:(Ljava/lang/Object;)Z
const #14 = class	#49;	//  java/lang/StringBuilder
const #15 = Method	#14.#34;	//  java/lang/StringBuilder."<init>":()V
const #16 = String	#50;	//  Found system package with name: 
const #17 = Method	#14.#51;	//  java/lang/StringBuilder.append:(Ljava/lang/String;)Ljava/lang/StringBuilder;
const #18 = Method	#14.#52;	//  java/lang/StringBuilder.toString:()Ljava/lang/String;
const #19 = class	#53;	//  classes/test/PackageTest
const #20 = class	#54;	//  java/lang/Object
const #21 = Asciz	<init>;
const #22 = Asciz	()V;
const #23 = Asciz	Code;
const #24 = Asciz	LineNumberTable;
const #25 = Asciz	main;
const #26 = Asciz	([Ljava/lang/String;)V;
const #27 = Asciz	StackMapTable;
const #28 = class	#55;	//  "[Ljava/lang/String;"
const #29 = class	#56;	//  java/lang/Package
const #30 = class	#57;	//  "[Ljava/lang/Package;"
const #31 = class	#44;	//  java/util/HashSet
const #32 = Asciz	SourceFile;
const #33 = Asciz	PackageTest.java;
const #34 = NameAndType	#21:#22;//  "<init>":()V
const #35 = Asciz	java.lang;
const #36 = class	#56;	//  java/lang/Package
const #37 = NameAndType	#58:#59;//  getPackage:(Ljava/lang/String;)Ljava/lang/Package;
const #38 = class	#60;	//  java/lang/System
const #39 = NameAndType	#61:#62;//  out:Ljava/io/PrintStream;
const #40 = NameAndType	#63:#64;//  getName:()Ljava/lang/String;
const #41 = class	#65;	//  java/io/PrintStream
const #42 = NameAndType	#66:#67;//  println:(Ljava/lang/String;)V
const #43 = NameAndType	#68:#69;//  getPackages:()[Ljava/lang/Package;
const #44 = Asciz	java/util/HashSet;
const #45 = NameAndType	#70:#71;//  add:(Ljava/lang/Object;)Z
const #46 = Asciz	java.io;
const #47 = Asciz	java.util;
const #48 = NameAndType	#72:#71;//  contains:(Ljava/lang/Object;)Z
const #49 = Asciz	java/lang/StringBuilder;
const #50 = Asciz	Found system package with name: ;
const #51 = NameAndType	#73:#74;//  append:(Ljava/lang/String;)Ljava/lang/StringBuilder;
const #52 = NameAndType	#75:#64;//  toString:()Ljava/lang/String;
const #53 = Asciz	classes/test/PackageTest;
const #54 = Asciz	java/lang/Object;
const #55 = Asciz	[Ljava/lang/String;;
const #56 = Asciz	java/lang/Package;
const #57 = Asciz	[Ljava/lang/Package;;
const #58 = Asciz	getPackage;
const #59 = Asciz	(Ljava/lang/String;)Ljava/lang/Package;;
const #60 = Asciz	java/lang/System;
const #61 = Asciz	out;
const #62 = Asciz	Ljava/io/PrintStream;;
const #63 = Asciz	getName;
const #64 = Asciz	()Ljava/lang/String;;
const #65 = Asciz	java/io/PrintStream;
const #66 = Asciz	println;
const #67 = Asciz	(Ljava/lang/String;)V;
const #68 = Asciz	getPackages;
const #69 = Asciz	()[Ljava/lang/Package;;
const #70 = Asciz	add;
const #71 = Asciz	(Ljava/lang/Object;)Z;
const #72 = Asciz	contains;
const #73 = Asciz	append;
const #74 = Asciz	(Ljava/lang/String;)Ljava/lang/StringBuilder;;
const #75 = Asciz	toString;

{
classes.test.PackageTest();
  Code:
   Stack=1, Locals=1, Args_size=1
   0:	aload_0
   1:	invokespecial	#1; //Method java/lang/Object."<init>":()V
   4:	return
  LineNumberTable: 
   line 6: 0


public static void main(java.lang.String[]);
  Code:
   Stack=3, Locals=9, Args_size=1
   0:	ldc	#2; //String java.lang
   2:	invokestatic	#3; //Method java/lang/Package.getPackage:(Ljava/lang/String;)Ljava/lang/Package;
   5:	astore_1
   6:	getstatic	#4; //Field java/lang/System.out:Ljava/io/PrintStream;
   9:	aload_1
   10:	invokevirtual	#5; //Method java/lang/Package.getName:()Ljava/lang/String;
   13:	invokevirtual	#6; //Method java/io/PrintStream.println:(Ljava/lang/String;)V
   16:	invokestatic	#7; //Method java/lang/Package.getPackages:()[Ljava/lang/Package;
   19:	astore_2
   20:	new	#8; //class java/util/HashSet
   23:	dup
   24:	invokespecial	#9; //Method java/util/HashSet."<init>":()V
   27:	astore_3
   28:	aload_3
   29:	ldc	#2; //String java.lang
   31:	invokevirtual	#10; //Method java/util/HashSet.add:(Ljava/lang/Object;)Z
   34:	pop
   35:	aload_3
   36:	ldc	#11; //String java.io
   38:	invokevirtual	#10; //Method java/util/HashSet.add:(Ljava/lang/Object;)Z
   41:	pop
   42:	aload_3
   43:	ldc	#12; //String java.util
   45:	invokevirtual	#10; //Method java/util/HashSet.add:(Ljava/lang/Object;)Z
   48:	pop
   49:	aload_2
   50:	astore	4
   52:	aload	4
   54:	arraylength
   55:	istore	5
   57:	iconst_0
   58:	istore	6
   60:	iload	6
   62:	iload	5
   64:	if_icmpge	122
   67:	aload	4
   69:	iload	6
   71:	aaload
   72:	astore	7
   74:	aload	7
   76:	invokevirtual	#5; //Method java/lang/Package.getName:()Ljava/lang/String;
   79:	astore	8
   81:	aload_3
   82:	aload	8
   84:	invokevirtual	#13; //Method java/util/HashSet.contains:(Ljava/lang/Object;)Z
   87:	ifeq	116
   90:	getstatic	#4; //Field java/lang/System.out:Ljava/io/PrintStream;
   93:	new	#14; //class java/lang/StringBuilder
   96:	dup
   97:	invokespecial	#15; //Method java/lang/StringBuilder."<init>":()V
   100:	ldc	#16; //String Found system package with name: 
   102:	invokevirtual	#17; //Method java/lang/StringBuilder.append:(Ljava/lang/String;)Ljava/lang/StringBuilder;
   105:	aload	8
   107:	invokevirtual	#17; //Method java/lang/StringBuilder.append:(Ljava/lang/String;)Ljava/lang/StringBuilder;
   110:	invokevirtual	#18; //Method java/lang/StringBuilder.toString:()Ljava/lang/String;
   113:	invokevirtual	#6; //Method java/io/PrintStream.println:(Ljava/lang/String;)V
   116:	iinc	6, 1
   119:	goto	60
   122:	return
  LineNumberTable: 
   line 8: 0
   line 9: 6
   line 11: 16
   line 14: 20
   line 15: 28
   line 16: 35
   line 17: 42
   line 18: 49
   line 19: 74
   line 20: 81
   line 21: 90
   line 18: 116
   line 23: 122

  StackMapTable: number_of_entries = 3
   frame_type = 255 /* full_frame */
     offset_delta = 60
     locals = [ class "[Ljava/lang/String;", class java/lang/Package, class "[Ljava/lang/Package;", class java/util/HashSet, class "[Ljava/lang/Package;", int, int ]
     stack = []
   frame_type = 55 /* same */
   frame_type = 248 /* chop */
     offset_delta = 5


}

