Compiled from "ParkUnpark.java"
public class classes.test.ParkUnpark extends java.lang.Object
  SourceFile: "ParkUnpark.java"
  InnerClass: 
   #18= #9 of #16; //PrintThread=class classes/test/ParkUnpark$PrintThread of class classes/test/ParkUnpark
   #20= #14 of #16; //FIFOMutex=class classes/test/ParkUnpark$FIFOMutex of class classes/test/ParkUnpark
   #21= #3 of #16; //TimeoutTest=class classes/test/ParkUnpark$TimeoutTest of class classes/test/ParkUnpark
  minor version: 0
  major version: 50
  Constant pool:
const #1 = Field	#16.#39;	//  classes/test/ParkUnpark.mut:Lclasses/test/ParkUnpark$FIFOMutex;
const #2 = Method	#17.#40;	//  java/lang/Object."<init>":()V
const #3 = class	#41;	//  classes/test/ParkUnpark$TimeoutTest
const #4 = Method	#3.#40;	//  classes/test/ParkUnpark$TimeoutTest."<init>":()V
const #5 = Method	#3.#42;	//  classes/test/ParkUnpark$TimeoutTest.start:()V
const #6 = Method	#3.#43;	//  classes/test/ParkUnpark$TimeoutTest.isAlive:()Z
const #7 = Method	#44.#45;	//  java/lang/Thread.yield:()V
const #8 = Method	#14.#46;	//  classes/test/ParkUnpark$FIFOMutex.lock:()V
const #9 = class	#47;	//  classes/test/ParkUnpark$PrintThread
const #10 = String	#48;	//  Message
const #11 = Method	#9.#49;	//  classes/test/ParkUnpark$PrintThread."<init>":(Ljava/lang/String;)V
const #12 = Method	#9.#42;	//  classes/test/ParkUnpark$PrintThread.start:()V
const #13 = Method	#14.#50;	//  classes/test/ParkUnpark$FIFOMutex.unlock:()V
const #14 = class	#51;	//  classes/test/ParkUnpark$FIFOMutex
const #15 = Method	#14.#40;	//  classes/test/ParkUnpark$FIFOMutex."<init>":()V
const #16 = class	#52;	//  classes/test/ParkUnpark
const #17 = class	#53;	//  java/lang/Object
const #18 = Asciz	PrintThread;
const #19 = Asciz	InnerClasses;
const #20 = Asciz	FIFOMutex;
const #21 = Asciz	TimeoutTest;
const #22 = Asciz	mut;
const #23 = Asciz	Lclasses/test/ParkUnpark$FIFOMutex;;
const #24 = Asciz	<init>;
const #25 = Asciz	()V;
const #26 = Asciz	Code;
const #27 = Asciz	LineNumberTable;
const #28 = Asciz	main;
const #29 = Asciz	([Ljava/lang/String;)V;
const #30 = Asciz	StackMapTable;
const #31 = class	#41;	//  classes/test/ParkUnpark$TimeoutTest
const #32 = Asciz	Exceptions;
const #33 = class	#54;	//  java/lang/InterruptedException
const #34 = Asciz	access$000;
const #35 = Asciz	()Lclasses/test/ParkUnpark$FIFOMutex;;
const #36 = Asciz	<clinit>;
const #37 = Asciz	SourceFile;
const #38 = Asciz	ParkUnpark.java;
const #39 = NameAndType	#22:#23;//  mut:Lclasses/test/ParkUnpark$FIFOMutex;
const #40 = NameAndType	#24:#25;//  "<init>":()V
const #41 = Asciz	classes/test/ParkUnpark$TimeoutTest;
const #42 = NameAndType	#55:#25;//  start:()V
const #43 = NameAndType	#56:#57;//  isAlive:()Z
const #44 = class	#58;	//  java/lang/Thread
const #45 = NameAndType	#59:#25;//  yield:()V
const #46 = NameAndType	#60:#25;//  lock:()V
const #47 = Asciz	classes/test/ParkUnpark$PrintThread;
const #48 = Asciz	Message;
const #49 = NameAndType	#24:#61;//  "<init>":(Ljava/lang/String;)V
const #50 = NameAndType	#62:#25;//  unlock:()V
const #51 = Asciz	classes/test/ParkUnpark$FIFOMutex;
const #52 = Asciz	classes/test/ParkUnpark;
const #53 = Asciz	java/lang/Object;
const #54 = Asciz	java/lang/InterruptedException;
const #55 = Asciz	start;
const #56 = Asciz	isAlive;
const #57 = Asciz	()Z;
const #58 = Asciz	java/lang/Thread;
const #59 = Asciz	yield;
const #60 = Asciz	lock;
const #61 = Asciz	(Ljava/lang/String;)V;
const #62 = Asciz	unlock;

{
private static final classes.test.ParkUnpark$FIFOMutex mut;


public classes.test.ParkUnpark();
  Code:
   Stack=1, Locals=1, Args_size=1
   0:	aload_0
   1:	invokespecial	#2; //Method java/lang/Object."<init>":()V
   4:	return
  LineNumberTable: 
   line 9: 0
   line 49: 4


public static void main(java.lang.String[])   throws java.lang.InterruptedException;
  Code:
   Stack=3, Locals=2, Args_size=1
   0:	new	#3; //class classes/test/ParkUnpark$TimeoutTest
   3:	dup
   4:	invokespecial	#4; //Method classes/test/ParkUnpark$TimeoutTest."<init>":()V
   7:	astore_1
   8:	aload_1
   9:	invokevirtual	#5; //Method classes/test/ParkUnpark$TimeoutTest.start:()V
   12:	aload_1
   13:	invokevirtual	#6; //Method classes/test/ParkUnpark$TimeoutTest.isAlive:()Z
   16:	ifeq	25
   19:	invokestatic	#7; //Method java/lang/Thread.yield:()V
   22:	goto	12
   25:	getstatic	#1; //Field mut:Lclasses/test/ParkUnpark$FIFOMutex;
   28:	invokevirtual	#8; //Method classes/test/ParkUnpark$FIFOMutex.lock:()V
   31:	new	#9; //class classes/test/ParkUnpark$PrintThread
   34:	dup
   35:	ldc	#10; //String Message
   37:	invokespecial	#11; //Method classes/test/ParkUnpark$PrintThread."<init>":(Ljava/lang/String;)V
   40:	invokevirtual	#12; //Method classes/test/ParkUnpark$PrintThread.start:()V
   43:	new	#9; //class classes/test/ParkUnpark$PrintThread
   46:	dup
   47:	ldc	#10; //String Message
   49:	invokespecial	#11; //Method classes/test/ParkUnpark$PrintThread."<init>":(Ljava/lang/String;)V
   52:	invokevirtual	#12; //Method classes/test/ParkUnpark$PrintThread.start:()V
   55:	new	#9; //class classes/test/ParkUnpark$PrintThread
   58:	dup
   59:	ldc	#10; //String Message
   61:	invokespecial	#11; //Method classes/test/ParkUnpark$PrintThread."<init>":(Ljava/lang/String;)V
   64:	invokevirtual	#12; //Method classes/test/ParkUnpark$PrintThread.start:()V
   67:	getstatic	#1; //Field mut:Lclasses/test/ParkUnpark$FIFOMutex;
   70:	invokevirtual	#13; //Method classes/test/ParkUnpark$FIFOMutex.unlock:()V
   73:	return
  LineNumberTable: 
   line 62: 0
   line 63: 8
   line 64: 12
   line 66: 25
   line 67: 31
   line 68: 43
   line 69: 55
   line 70: 67
   line 71: 73

  StackMapTable: number_of_entries = 2
   frame_type = 252 /* append */
     offset_delta = 12
     locals = [ class classes/test/ParkUnpark$TimeoutTest ]
   frame_type = 12 /* same */

  Exceptions: 
   throws java.lang.InterruptedException
static classes.test.ParkUnpark$FIFOMutex access$000();
  Code:
   Stack=1, Locals=0, Args_size=0
   0:	getstatic	#1; //Field mut:Lclasses/test/ParkUnpark$FIFOMutex;
   3:	areturn
  LineNumberTable: 
   line 9: 0


static {};
  Code:
   Stack=2, Locals=0, Args_size=0
   0:	new	#14; //class classes/test/ParkUnpark$FIFOMutex
   3:	dup
   4:	invokespecial	#15; //Method classes/test/ParkUnpark$FIFOMutex."<init>":()V
   7:	putstatic	#1; //Field mut:Lclasses/test/ParkUnpark$FIFOMutex;
   10:	return
  LineNumberTable: 
   line 47: 0


}

