Compiled from "Reflection.java"
public class classes.test.Reflection extends java.lang.Object
  SourceFile: "Reflection.java"
  InnerClass: 
   #110= #24 of #19; //SubClass=class classes/test/Reflection$SubClass of class classes/test/Reflection
   abstract #112= #29 of #19; //Iface=class classes/test/Reflection$Iface of class classes/test/Reflection
   #188= #10; //InMethod=class classes/test/Reflection$1InMethod
  minor version: 0
  major version: 50
  Constant pool:
const #1 = Method	#32.#176;	//  java/lang/Object."<init>":()V
const #2 = String	#177;	//  I'm a good string
const #3 = Field	#19.#178;	//  classes/test/Reflection.goodString:Ljava/lang/String;
const #4 = class	#179;	//  java/lang/Long
const #5 = Method	#4.#180;	//  java/lang/Long.longValue:()J
const #6 = Method	#4.#181;	//  java/lang/Long."<init>":(J)V
const #7 = Field	#182.#183;	//  java/lang/System.out:Ljava/io/PrintStream;
const #8 = String	#184;	//  called foo
const #9 = Method	#185.#186;	//  java/io/PrintStream.println:(Ljava/lang/String;)V
const #10 = class	#187;	//  classes/test/Reflection$1InMethod
const #11 = Method	#10.#176;	//  classes/test/Reflection$1InMethod."<init>":()V
const #12 = Field	#84.#189;	//  java/lang/Integer.TYPE:Ljava/lang/Class;
const #13 = Method	#190.#191;	//  java/lang/reflect/Array.newInstance:(Ljava/lang/Class;I)Ljava/lang/Object;
const #14 = class	#192;	//  "[I"
const #15 = Method	#193.#194;	//  java/util/Arrays.toString:([I)Ljava/lang/String;
const #16 = Method	#190.#195;	//  java/lang/reflect/Array.newInstance:(Ljava/lang/Class;[I)Ljava/lang/Object;
const #17 = class	#196;	//  "[[I"
const #18 = Method	#193.#197;	//  java/util/Arrays.deepToString:([Ljava/lang/Object;)Ljava/lang/String;
const #19 = class	#198;	//  classes/test/Reflection
const #20 = Method	#31.#199;	//  java/lang/Class.getEnclosingMethod:()Ljava/lang/reflect/Method;
const #21 = Method	#185.#200;	//  java/io/PrintStream.println:(Ljava/lang/Object;)V
const #22 = Method	#19.#201;	//  classes/test/Reflection.classInMethod:()Ljava/lang/Object;
const #23 = Method	#32.#202;	//  java/lang/Object.getClass:()Ljava/lang/Class;
const #24 = class	#203;	//  classes/test/Reflection$SubClass
const #25 = Method	#24.#176;	//  classes/test/Reflection$SubClass."<init>":()V
const #26 = String	#113;	//  goodString
const #27 = Method	#31.#204;	//  java/lang/Class.getDeclaredField:(Ljava/lang/String;)Ljava/lang/reflect/Field;
const #28 = Method	#205.#206;	//  java/lang/reflect/Field.get:(Ljava/lang/Object;)Ljava/lang/Object;
const #29 = class	#207;	//  classes/test/Reflection$Iface
const #30 = String	#208;	//  inYourIface
const #31 = class	#209;	//  java/lang/Class
const #32 = class	#210;	//  java/lang/Object
const #33 = Method	#31.#211;	//  java/lang/Class.getMethod:(Ljava/lang/String;[Ljava/lang/Class;)Ljava/lang/reflect/Method;
const #34 = String	#145;	//  foo
const #35 = Method	#212.#213;	//  java/lang/reflect/Method.invoke:(Ljava/lang/Object;[Ljava/lang/Object;)Ljava/lang/Object;
const #36 = Method	#19.#176;	//  classes/test/Reflection."<init>":()V
const #37 = String	#115;	//  constValue
const #38 = Method	#31.#214;	//  java/lang/Class.getField:(Ljava/lang/String;)Ljava/lang/reflect/Field;
const #39 = String	#118;	//  constInt
const #40 = String	#121;	//  constFloat
const #41 = String	#124;	//  constDouble
const #42 = String	#128;	//  constLong
const #43 = String	#132;	//  constShort
const #44 = String	#135;	//  constBool
const #45 = String	#215;	//  toString
const #46 = String	#216;	//  isArray
const #47 = String	#217;	//  isInstance
const #48 = String	#142;	//  add
const #49 = Field	#4.#189;	//  java/lang/Long.TYPE:Ljava/lang/Class;
const #50 = class	#218;	//  java/lang/StringBuilder
const #51 = Method	#50.#176;	//  java/lang/StringBuilder."<init>":()V
const #52 = String	#219;	//  toString: 
const #53 = Method	#50.#220;	//  java/lang/StringBuilder.append:(Ljava/lang/String;)Ljava/lang/StringBuilder;
const #54 = Method	#50.#221;	//  java/lang/StringBuilder.append:(Ljava/lang/Object;)Ljava/lang/StringBuilder;
const #55 = Method	#50.#222;	//  java/lang/StringBuilder.toString:()Ljava/lang/String;
const #56 = String	#223;	//  is array? 
const #57 = String	#224;	//  is instance? 
const #58 = long	40l;
const #60 = long	2l;
const #62 = String	#225;	//  unboxing: 
const #63 = String	#226;	//  boxing: 
const #64 = long	1300l;
const #66 = Method	#4.#227;	//  java/lang/Long.valueOf:(J)Ljava/lang/Long;
const #67 = long	37l;
const #69 = String	#228;	//  void return: 
const #70 = String	#229;	//  Testing java.lang.reflect.Array.set
const #71 = class	#230;	//  java/lang/Byte
const #72 = Method	#71.#231;	//  java/lang/Byte."<init>":(B)V
const #73 = Method	#190.#232;	//  java/lang/reflect/Array.set:(Ljava/lang/Object;ILjava/lang/Object;)V
const #74 = Method	#185.#233;	//  java/io/PrintStream.println:(I)V
const #75 = class	#234;	//  java/lang/Character
const #76 = Method	#75.#235;	//  java/lang/Character."<init>":(C)V
const #77 = Method	#185.#236;	//  java/io/PrintStream.println:(C)V
const #78 = class	#237;	//  java/lang/Double
const #79 = Method	#78.#238;	//  java/lang/Double."<init>":(D)V
const #80 = Method	#185.#239;	//  java/io/PrintStream.println:(D)V
const #81 = class	#240;	//  java/lang/Float
const #82 = Method	#81.#241;	//  java/lang/Float."<init>":(F)V
const #83 = Method	#185.#242;	//  java/io/PrintStream.println:(F)V
const #84 = class	#243;	//  java/lang/Integer
const #85 = Method	#84.#244;	//  java/lang/Integer."<init>":(I)V
const #86 = Method	#185.#245;	//  java/io/PrintStream.println:(J)V
const #87 = class	#246;	//  java/lang/Short
const #88 = Method	#87.#247;	//  java/lang/Short."<init>":(S)V
const #89 = class	#248;	//  java/lang/Boolean
const #90 = Method	#89.#249;	//  java/lang/Boolean."<init>":(Z)V
const #91 = Method	#185.#250;	//  java/io/PrintStream.println:(Z)V
const #92 = Method	#31.#251;	//  java/lang/Class.getName:()Ljava/lang/String;
const #93 = String	#252;	//  Checking Array.set's exceptions
const #94 = class	#253;	//  java/lang/ArrayIndexOutOfBoundsException
const #95 = String	#254;	//  Caught ArrayIndexOutOfBoundsException
const #96 = class	#255;	//  java/lang/IllegalArgumentException
const #97 = String	#256;	//  Caught IllegalArgumentException
const #98 = String	#257;	//  Testing java.lang.reflect.Array.get*
const #99 = Method	#190.#258;	//  java/lang/reflect/Array.getLength:(Ljava/lang/Object;)I
const #100 = Method	#190.#259;	//  java/lang/reflect/Array.getByte:(Ljava/lang/Object;I)B
const #101 = Method	#190.#260;	//  java/lang/reflect/Array.getChar:(Ljava/lang/Object;I)C
const #102 = Method	#190.#261;	//  java/lang/reflect/Array.getDouble:(Ljava/lang/Object;I)D
const #103 = Method	#190.#262;	//  java/lang/reflect/Array.getFloat:(Ljava/lang/Object;I)F
const #104 = Method	#190.#263;	//  java/lang/reflect/Array.getInt:(Ljava/lang/Object;I)I
const #105 = Method	#190.#264;	//  java/lang/reflect/Array.getLong:(Ljava/lang/Object;I)J
const #106 = Method	#190.#265;	//  java/lang/reflect/Array.getShort:(Ljava/lang/Object;I)S
const #107 = Method	#190.#266;	//  java/lang/reflect/Array.getBoolean:(Ljava/lang/Object;I)Z
const #108 = Method	#190.#267;	//  java/lang/reflect/Array.get:(Ljava/lang/Object;I)Ljava/lang/Object;
const #109 = String	#268;	//  Checking Array.get*'s exceptions
const #110 = Asciz	SubClass;
const #111 = Asciz	InnerClasses;
const #112 = Asciz	Iface;
const #113 = Asciz	goodString;
const #114 = Asciz	Ljava/lang/String;;
const #115 = Asciz	constValue;
const #116 = Asciz	ConstantValue;
const #117 = String	#269;	//  I'm a constant
const #118 = Asciz	constInt;
const #119 = Asciz	I;
const #120 = int	23;
const #121 = Asciz	constFloat;
const #122 = Asciz	F;
const #123 = float	2.45f;
const #124 = Asciz	constDouble;
const #125 = Asciz	D;
const #126 = double	1.4567d;
const #128 = Asciz	constLong;
const #129 = Asciz	J;
const #130 = long	8394834397l;
const #132 = Asciz	constShort;
const #133 = Asciz	S;
const #134 = int	12;
const #135 = Asciz	constBool;
const #136 = Asciz	Z;
const #137 = int	1;
const #138 = Asciz	<init>;
const #139 = Asciz	()V;
const #140 = Asciz	Code;
const #141 = Asciz	LineNumberTable;
const #142 = Asciz	add;
const #143 = Asciz	(JJ)J;
const #144 = Asciz	(Ljava/lang/Long;Ljava/lang/Long;)Ljava/lang/Long;;
const #145 = Asciz	foo;
const #146 = Asciz	classInMethod;
const #147 = Asciz	()Ljava/lang/Object;;
const #148 = Asciz	main;
const #149 = Asciz	([Ljava/lang/String;)V;
const #150 = Asciz	StackMapTable;
const #151 = class	#270;	//  "[Ljava/lang/String;"
const #152 = class	#203;	//  classes/test/Reflection$SubClass
const #153 = class	#271;	//  java/lang/reflect/Field
const #154 = class	#272;	//  java/lang/reflect/Method
const #155 = class	#198;	//  classes/test/Reflection
const #156 = class	#209;	//  java/lang/Class
const #157 = class	#179;	//  java/lang/Long
const #158 = class	#273;	//  "[B"
const #159 = class	#274;	//  "[C"
const #160 = class	#275;	//  "[D"
const #161 = class	#276;	//  "[F"
const #162 = class	#277;	//  "[J"
const #163 = class	#278;	//  "[S"
const #164 = class	#279;	//  "[Z"
const #165 = class	#280;	//  "[Ljava/lang/Integer;"
const #166 = class	#253;	//  java/lang/ArrayIndexOutOfBoundsException
const #167 = class	#255;	//  java/lang/IllegalArgumentException
const #168 = Asciz	Exceptions;
const #169 = class	#281;	//  java/lang/ClassNotFoundException
const #170 = class	#282;	//  java/lang/NoSuchMethodException
const #171 = class	#283;	//  java/lang/IllegalAccessException
const #172 = class	#284;	//  java/lang/reflect/InvocationTargetException
const #173 = class	#285;	//  java/lang/NoSuchFieldException
const #174 = Asciz	SourceFile;
const #175 = Asciz	Reflection.java;
const #176 = NameAndType	#138:#139;//  "<init>":()V
const #177 = Asciz	I'm a good string;
const #178 = NameAndType	#113:#114;//  goodString:Ljava/lang/String;
const #179 = Asciz	java/lang/Long;
const #180 = NameAndType	#286:#287;//  longValue:()J
const #181 = NameAndType	#138:#288;//  "<init>":(J)V
const #182 = class	#289;	//  java/lang/System
const #183 = NameAndType	#290:#291;//  out:Ljava/io/PrintStream;
const #184 = Asciz	called foo;
const #185 = class	#292;	//  java/io/PrintStream
const #186 = NameAndType	#293:#294;//  println:(Ljava/lang/String;)V
const #187 = Asciz	classes/test/Reflection$1InMethod;
const #188 = Asciz	InMethod;
const #189 = NameAndType	#295:#296;//  TYPE:Ljava/lang/Class;
const #190 = class	#297;	//  java/lang/reflect/Array
const #191 = NameAndType	#298:#299;//  newInstance:(Ljava/lang/Class;I)Ljava/lang/Object;
const #192 = Asciz	[I;
const #193 = class	#300;	//  java/util/Arrays
const #194 = NameAndType	#215:#301;//  toString:([I)Ljava/lang/String;
const #195 = NameAndType	#298:#302;//  newInstance:(Ljava/lang/Class;[I)Ljava/lang/Object;
const #196 = Asciz	[[I;
const #197 = NameAndType	#303:#304;//  deepToString:([Ljava/lang/Object;)Ljava/lang/String;
const #198 = Asciz	classes/test/Reflection;
const #199 = NameAndType	#305:#306;//  getEnclosingMethod:()Ljava/lang/reflect/Method;
const #200 = NameAndType	#293:#307;//  println:(Ljava/lang/Object;)V
const #201 = NameAndType	#146:#147;//  classInMethod:()Ljava/lang/Object;
const #202 = NameAndType	#308:#309;//  getClass:()Ljava/lang/Class;
const #203 = Asciz	classes/test/Reflection$SubClass;
const #204 = NameAndType	#310:#311;//  getDeclaredField:(Ljava/lang/String;)Ljava/lang/reflect/Field;
const #205 = class	#271;	//  java/lang/reflect/Field
const #206 = NameAndType	#312:#313;//  get:(Ljava/lang/Object;)Ljava/lang/Object;
const #207 = Asciz	classes/test/Reflection$Iface;
const #208 = Asciz	inYourIface;
const #209 = Asciz	java/lang/Class;
const #210 = Asciz	java/lang/Object;
const #211 = NameAndType	#314:#315;//  getMethod:(Ljava/lang/String;[Ljava/lang/Class;)Ljava/lang/reflect/Method;
const #212 = class	#272;	//  java/lang/reflect/Method
const #213 = NameAndType	#316:#317;//  invoke:(Ljava/lang/Object;[Ljava/lang/Object;)Ljava/lang/Object;
const #214 = NameAndType	#318:#311;//  getField:(Ljava/lang/String;)Ljava/lang/reflect/Field;
const #215 = Asciz	toString;
const #216 = Asciz	isArray;
const #217 = Asciz	isInstance;
const #218 = Asciz	java/lang/StringBuilder;
const #219 = Asciz	toString: ;
const #220 = NameAndType	#319:#320;//  append:(Ljava/lang/String;)Ljava/lang/StringBuilder;
const #221 = NameAndType	#319:#321;//  append:(Ljava/lang/Object;)Ljava/lang/StringBuilder;
const #222 = NameAndType	#215:#322;//  toString:()Ljava/lang/String;
const #223 = Asciz	is array? ;
const #224 = Asciz	is instance? ;
const #225 = Asciz	unboxing: ;
const #226 = Asciz	boxing: ;
const #227 = NameAndType	#323:#324;//  valueOf:(J)Ljava/lang/Long;
const #228 = Asciz	void return: ;
const #229 = Asciz	Testing java.lang.reflect.Array.set;
const #230 = Asciz	java/lang/Byte;
const #231 = NameAndType	#138:#325;//  "<init>":(B)V
const #232 = NameAndType	#326:#327;//  set:(Ljava/lang/Object;ILjava/lang/Object;)V
const #233 = NameAndType	#293:#328;//  println:(I)V
const #234 = Asciz	java/lang/Character;
const #235 = NameAndType	#138:#329;//  "<init>":(C)V
const #236 = NameAndType	#293:#329;//  println:(C)V
const #237 = Asciz	java/lang/Double;
const #238 = NameAndType	#138:#330;//  "<init>":(D)V
const #239 = NameAndType	#293:#330;//  println:(D)V
const #240 = Asciz	java/lang/Float;
const #241 = NameAndType	#138:#331;//  "<init>":(F)V
const #242 = NameAndType	#293:#331;//  println:(F)V
const #243 = Asciz	java/lang/Integer;
const #244 = NameAndType	#138:#328;//  "<init>":(I)V
const #245 = NameAndType	#293:#288;//  println:(J)V
const #246 = Asciz	java/lang/Short;
const #247 = NameAndType	#138:#332;//  "<init>":(S)V
const #248 = Asciz	java/lang/Boolean;
const #249 = NameAndType	#138:#333;//  "<init>":(Z)V
const #250 = NameAndType	#293:#333;//  println:(Z)V
const #251 = NameAndType	#334:#322;//  getName:()Ljava/lang/String;
const #252 = Asciz	Checking Array.set's exceptions;
const #253 = Asciz	java/lang/ArrayIndexOutOfBoundsException;
const #254 = Asciz	Caught ArrayIndexOutOfBoundsException;
const #255 = Asciz	java/lang/IllegalArgumentException;
const #256 = Asciz	Caught IllegalArgumentException;
const #257 = Asciz	Testing java.lang.reflect.Array.get*;
const #258 = NameAndType	#335:#336;//  getLength:(Ljava/lang/Object;)I
const #259 = NameAndType	#337:#338;//  getByte:(Ljava/lang/Object;I)B
const #260 = NameAndType	#339:#340;//  getChar:(Ljava/lang/Object;I)C
const #261 = NameAndType	#341:#342;//  getDouble:(Ljava/lang/Object;I)D
const #262 = NameAndType	#343:#344;//  getFloat:(Ljava/lang/Object;I)F
const #263 = NameAndType	#345:#346;//  getInt:(Ljava/lang/Object;I)I
const #264 = NameAndType	#347:#348;//  getLong:(Ljava/lang/Object;I)J
const #265 = NameAndType	#349:#350;//  getShort:(Ljava/lang/Object;I)S
const #266 = NameAndType	#351:#352;//  getBoolean:(Ljava/lang/Object;I)Z
const #267 = NameAndType	#312:#353;//  get:(Ljava/lang/Object;I)Ljava/lang/Object;
const #268 = Asciz	Checking Array.get*'s exceptions;
const #269 = Asciz	I'm a constant;
const #270 = Asciz	[Ljava/lang/String;;
const #271 = Asciz	java/lang/reflect/Field;
const #272 = Asciz	java/lang/reflect/Method;
const #273 = Asciz	[B;
const #274 = Asciz	[C;
const #275 = Asciz	[D;
const #276 = Asciz	[F;
const #277 = Asciz	[J;
const #278 = Asciz	[S;
const #279 = Asciz	[Z;
const #280 = Asciz	[Ljava/lang/Integer;;
const #281 = Asciz	java/lang/ClassNotFoundException;
const #282 = Asciz	java/lang/NoSuchMethodException;
const #283 = Asciz	java/lang/IllegalAccessException;
const #284 = Asciz	java/lang/reflect/InvocationTargetException;
const #285 = Asciz	java/lang/NoSuchFieldException;
const #286 = Asciz	longValue;
const #287 = Asciz	()J;
const #288 = Asciz	(J)V;
const #289 = Asciz	java/lang/System;
const #290 = Asciz	out;
const #291 = Asciz	Ljava/io/PrintStream;;
const #292 = Asciz	java/io/PrintStream;
const #293 = Asciz	println;
const #294 = Asciz	(Ljava/lang/String;)V;
const #295 = Asciz	TYPE;
const #296 = Asciz	Ljava/lang/Class;;
const #297 = Asciz	java/lang/reflect/Array;
const #298 = Asciz	newInstance;
const #299 = Asciz	(Ljava/lang/Class;I)Ljava/lang/Object;;
const #300 = Asciz	java/util/Arrays;
const #301 = Asciz	([I)Ljava/lang/String;;
const #302 = Asciz	(Ljava/lang/Class;[I)Ljava/lang/Object;;
const #303 = Asciz	deepToString;
const #304 = Asciz	([Ljava/lang/Object;)Ljava/lang/String;;
const #305 = Asciz	getEnclosingMethod;
const #306 = Asciz	()Ljava/lang/reflect/Method;;
const #307 = Asciz	(Ljava/lang/Object;)V;
const #308 = Asciz	getClass;
const #309 = Asciz	()Ljava/lang/Class;;
const #310 = Asciz	getDeclaredField;
const #311 = Asciz	(Ljava/lang/String;)Ljava/lang/reflect/Field;;
const #312 = Asciz	get;
const #313 = Asciz	(Ljava/lang/Object;)Ljava/lang/Object;;
const #314 = Asciz	getMethod;
const #315 = Asciz	(Ljava/lang/String;[Ljava/lang/Class;)Ljava/lang/reflect/Method;;
const #316 = Asciz	invoke;
const #317 = Asciz	(Ljava/lang/Object;[Ljava/lang/Object;)Ljava/lang/Object;;
const #318 = Asciz	getField;
const #319 = Asciz	append;
const #320 = Asciz	(Ljava/lang/String;)Ljava/lang/StringBuilder;;
const #321 = Asciz	(Ljava/lang/Object;)Ljava/lang/StringBuilder;;
const #322 = Asciz	()Ljava/lang/String;;
const #323 = Asciz	valueOf;
const #324 = Asciz	(J)Ljava/lang/Long;;
const #325 = Asciz	(B)V;
const #326 = Asciz	set;
const #327 = Asciz	(Ljava/lang/Object;ILjava/lang/Object;)V;
const #328 = Asciz	(I)V;
const #329 = Asciz	(C)V;
const #330 = Asciz	(D)V;
const #331 = Asciz	(F)V;
const #332 = Asciz	(S)V;
const #333 = Asciz	(Z)V;
const #334 = Asciz	getName;
const #335 = Asciz	getLength;
const #336 = Asciz	(Ljava/lang/Object;)I;
const #337 = Asciz	getByte;
const #338 = Asciz	(Ljava/lang/Object;I)B;
const #339 = Asciz	getChar;
const #340 = Asciz	(Ljava/lang/Object;I)C;
const #341 = Asciz	getDouble;
const #342 = Asciz	(Ljava/lang/Object;I)D;
const #343 = Asciz	getFloat;
const #344 = Asciz	(Ljava/lang/Object;I)F;
const #345 = Asciz	getInt;
const #346 = Asciz	(Ljava/lang/Object;I)I;
const #347 = Asciz	getLong;
const #348 = Asciz	(Ljava/lang/Object;I)J;
const #349 = Asciz	getShort;
const #350 = Asciz	(Ljava/lang/Object;I)S;
const #351 = Asciz	getBoolean;
const #352 = Asciz	(Ljava/lang/Object;I)Z;
const #353 = Asciz	(Ljava/lang/Object;I)Ljava/lang/Object;;

{
public java.lang.String goodString;


public static final java.lang.String constValue;
  Constant value: String I'm a constant

public static final int constInt;
  Constant value: int 23

public static final float constFloat;
  Constant value: float 2.45f

public static final double constDouble;
  Constant value: double 1.4567d

public static final long constLong;
  Constant value: long 8394834397l

public static final short constShort;
  Constant value: int 12

public static final boolean constBool;
  Constant value: int 1

public classes.test.Reflection();
  Code:
   Stack=2, Locals=1, Args_size=1
   0:	aload_0
   1:	invokespecial	#1; //Method java/lang/Object."<init>":()V
   4:	aload_0
   5:	ldc	#2; //String I'm a good string
   7:	putfield	#3; //Field goodString:Ljava/lang/String;
   10:	return
  LineNumberTable: 
   line 7: 0
   line 9: 4
   line 211: 10


public static long add(long, long);
  Code:
   Stack=4, Locals=4, Args_size=2
   0:	lload_0
   1:	lload_2
   2:	ladd
   3:	lreturn
  LineNumberTable: 
   line 19: 0


public static java.lang.Long add(java.lang.Long, java.lang.Long);
  Code:
   Stack=6, Locals=2, Args_size=2
   0:	new	#4; //class java/lang/Long
   3:	dup
   4:	aload_0
   5:	invokevirtual	#5; //Method java/lang/Long.longValue:()J
   8:	aload_1
   9:	invokevirtual	#5; //Method java/lang/Long.longValue:()J
   12:	ladd
   13:	invokespecial	#6; //Method java/lang/Long."<init>":(J)V
   16:	areturn
  LineNumberTable: 
   line 23: 0


public static void foo();
  Code:
   Stack=2, Locals=0, Args_size=0
   0:	getstatic	#7; //Field java/lang/System.out:Ljava/io/PrintStream;
   3:	ldc	#8; //String called foo
   5:	invokevirtual	#9; //Method java/io/PrintStream.println:(Ljava/lang/String;)V
   8:	return
  LineNumberTable: 
   line 27: 0
   line 28: 8


public static java.lang.Object classInMethod();
  Code:
   Stack=2, Locals=0, Args_size=0
   0:	new	#10; //class classes/test/Reflection$1InMethod
   3:	dup
   4:	invokespecial	#11; //Method classes/test/Reflection$1InMethod."<init>":()V
   7:	areturn
  LineNumberTable: 
   line 32: 0


public static void main(java.lang.String[])   throws java.lang.ClassNotFoundException, java.lang.NoSuchMethodException, java.lang.IllegalAccessException, java.lang.reflect.InvocationTargetException, java.lang.NoSuchFieldException;
  Code:
   Stack=9, Locals=33, Args_size=1
   0:	getstatic	#12; //Field java/lang/Integer.TYPE:Ljava/lang/Class;
   3:	iconst_4
   4:	invokestatic	#13; //Method java/lang/reflect/Array.newInstance:(Ljava/lang/Class;I)Ljava/lang/Object;
   7:	checkcast	#14; //class "[I"
   10:	checkcast	#14; //class "[I"
   13:	astore_1
   14:	getstatic	#7; //Field java/lang/System.out:Ljava/io/PrintStream;
   17:	aload_1
   18:	invokestatic	#15; //Method java/util/Arrays.toString:([I)Ljava/lang/String;
   21:	invokevirtual	#9; //Method java/io/PrintStream.println:(Ljava/lang/String;)V
   24:	getstatic	#12; //Field java/lang/Integer.TYPE:Ljava/lang/Class;
   27:	iconst_2
   28:	newarray int
   30:	dup
   31:	iconst_0
   32:	iconst_2
   33:	iastore
   34:	dup
   35:	iconst_1
   36:	iconst_3
   37:	iastore
   38:	invokestatic	#16; //Method java/lang/reflect/Array.newInstance:(Ljava/lang/Class;[I)Ljava/lang/Object;
   41:	checkcast	#17; //class "[[I"
   44:	checkcast	#17; //class "[[I"
   47:	astore_2
   48:	getstatic	#7; //Field java/lang/System.out:Ljava/io/PrintStream;
   51:	aload_2
   52:	invokestatic	#18; //Method java/util/Arrays.deepToString:([Ljava/lang/Object;)Ljava/lang/String;
   55:	invokevirtual	#9; //Method java/io/PrintStream.println:(Ljava/lang/String;)V
   58:	getstatic	#7; //Field java/lang/System.out:Ljava/io/PrintStream;
   61:	ldc_w	#19; //class classes/test/Reflection
   64:	invokevirtual	#20; //Method java/lang/Class.getEnclosingMethod:()Ljava/lang/reflect/Method;
   67:	invokevirtual	#21; //Method java/io/PrintStream.println:(Ljava/lang/Object;)V
   70:	getstatic	#7; //Field java/lang/System.out:Ljava/io/PrintStream;
   73:	invokestatic	#22; //Method classInMethod:()Ljava/lang/Object;
   76:	invokevirtual	#23; //Method java/lang/Object.getClass:()Ljava/lang/Class;
   79:	invokevirtual	#20; //Method java/lang/Class.getEnclosingMethod:()Ljava/lang/reflect/Method;
   82:	invokevirtual	#21; //Method java/io/PrintStream.println:(Ljava/lang/Object;)V
   85:	new	#24; //class classes/test/Reflection$SubClass
   88:	dup
   89:	invokespecial	#25; //Method classes/test/Reflection$SubClass."<init>":()V
   92:	astore_3
   93:	ldc_w	#19; //class classes/test/Reflection
   96:	ldc	#26; //String goodString
   98:	invokevirtual	#27; //Method java/lang/Class.getDeclaredField:(Ljava/lang/String;)Ljava/lang/reflect/Field;
   101:	astore	4
   103:	getstatic	#7; //Field java/lang/System.out:Ljava/io/PrintStream;
   106:	aload	4
   108:	aload_3
   109:	invokevirtual	#28; //Method java/lang/reflect/Field.get:(Ljava/lang/Object;)Ljava/lang/Object;
   112:	invokevirtual	#21; //Method java/io/PrintStream.println:(Ljava/lang/Object;)V
   115:	ldc_w	#29; //class classes/test/Reflection$Iface
   118:	ldc	#30; //String inYourIface
   120:	iconst_1
   121:	anewarray	#31; //class java/lang/Class
   124:	dup
   125:	iconst_0
   126:	ldc_w	#32; //class java/lang/Object
   129:	aastore
   130:	invokevirtual	#33; //Method java/lang/Class.getMethod:(Ljava/lang/String;[Ljava/lang/Class;)Ljava/lang/reflect/Method;
   133:	astore	5
   135:	aload	5
   137:	aload_3
   138:	iconst_1
   139:	anewarray	#32; //class java/lang/Object
   142:	dup
   143:	iconst_0
   144:	ldc	#34; //String foo
   146:	aastore
   147:	invokevirtual	#35; //Method java/lang/reflect/Method.invoke:(Ljava/lang/Object;[Ljava/lang/Object;)Ljava/lang/Object;
   150:	pop
   151:	new	#19; //class classes/test/Reflection
   154:	dup
   155:	invokespecial	#36; //Method "<init>":()V
   158:	astore	6
   160:	ldc_w	#19; //class classes/test/Reflection
   163:	astore	7
   165:	aload	7
   167:	ldc	#37; //String constValue
   169:	invokevirtual	#38; //Method java/lang/Class.getField:(Ljava/lang/String;)Ljava/lang/reflect/Field;
   172:	astore	8
   174:	getstatic	#7; //Field java/lang/System.out:Ljava/io/PrintStream;
   177:	aload	8
   179:	aconst_null
   180:	invokevirtual	#28; //Method java/lang/reflect/Field.get:(Ljava/lang/Object;)Ljava/lang/Object;
   183:	invokevirtual	#21; //Method java/io/PrintStream.println:(Ljava/lang/Object;)V
   186:	aload	7
   188:	ldc	#39; //String constInt
   190:	invokevirtual	#38; //Method java/lang/Class.getField:(Ljava/lang/String;)Ljava/lang/reflect/Field;
   193:	astore	9
   195:	getstatic	#7; //Field java/lang/System.out:Ljava/io/PrintStream;
   198:	aload	9
   200:	aconst_null
   201:	invokevirtual	#28; //Method java/lang/reflect/Field.get:(Ljava/lang/Object;)Ljava/lang/Object;
   204:	invokevirtual	#21; //Method java/io/PrintStream.println:(Ljava/lang/Object;)V
   207:	aload	7
   209:	ldc	#40; //String constFloat
   211:	invokevirtual	#38; //Method java/lang/Class.getField:(Ljava/lang/String;)Ljava/lang/reflect/Field;
   214:	astore	10
   216:	getstatic	#7; //Field java/lang/System.out:Ljava/io/PrintStream;
   219:	aload	10
   221:	aconst_null
   222:	invokevirtual	#28; //Method java/lang/reflect/Field.get:(Ljava/lang/Object;)Ljava/lang/Object;
   225:	invokevirtual	#21; //Method java/io/PrintStream.println:(Ljava/lang/Object;)V
   228:	aload	7
   230:	ldc	#41; //String constDouble
   232:	invokevirtual	#38; //Method java/lang/Class.getField:(Ljava/lang/String;)Ljava/lang/reflect/Field;
   235:	astore	11
   237:	getstatic	#7; //Field java/lang/System.out:Ljava/io/PrintStream;
   240:	aload	11
   242:	aconst_null
   243:	invokevirtual	#28; //Method java/lang/reflect/Field.get:(Ljava/lang/Object;)Ljava/lang/Object;
   246:	invokevirtual	#21; //Method java/io/PrintStream.println:(Ljava/lang/Object;)V
   249:	aload	7
   251:	ldc	#42; //String constLong
   253:	invokevirtual	#38; //Method java/lang/Class.getField:(Ljava/lang/String;)Ljava/lang/reflect/Field;
   256:	astore	12
   258:	getstatic	#7; //Field java/lang/System.out:Ljava/io/PrintStream;
   261:	aload	12
   263:	aconst_null
   264:	invokevirtual	#28; //Method java/lang/reflect/Field.get:(Ljava/lang/Object;)Ljava/lang/Object;
   267:	invokevirtual	#21; //Method java/io/PrintStream.println:(Ljava/lang/Object;)V
   270:	aload	7
   272:	ldc	#43; //String constShort
   274:	invokevirtual	#38; //Method java/lang/Class.getField:(Ljava/lang/String;)Ljava/lang/reflect/Field;
   277:	astore	13
   279:	getstatic	#7; //Field java/lang/System.out:Ljava/io/PrintStream;
   282:	aload	13
   284:	aconst_null
   285:	invokevirtual	#28; //Method java/lang/reflect/Field.get:(Ljava/lang/Object;)Ljava/lang/Object;
   288:	invokevirtual	#21; //Method java/io/PrintStream.println:(Ljava/lang/Object;)V
   291:	aload	7
   293:	ldc	#44; //String constBool
   295:	invokevirtual	#38; //Method java/lang/Class.getField:(Ljava/lang/String;)Ljava/lang/reflect/Field;
   298:	astore	14
   300:	getstatic	#7; //Field java/lang/System.out:Ljava/io/PrintStream;
   303:	aload	14
   305:	aconst_null
   306:	invokevirtual	#28; //Method java/lang/reflect/Field.get:(Ljava/lang/Object;)Ljava/lang/Object;
   309:	invokevirtual	#21; //Method java/io/PrintStream.println:(Ljava/lang/Object;)V
   312:	aload	7
   314:	invokevirtual	#23; //Method java/lang/Object.getClass:()Ljava/lang/Class;
   317:	ldc	#45; //String toString
   319:	iconst_0
   320:	anewarray	#31; //class java/lang/Class
   323:	invokevirtual	#33; //Method java/lang/Class.getMethod:(Ljava/lang/String;[Ljava/lang/Class;)Ljava/lang/reflect/Method;
   326:	astore	15
   328:	aload	7
   330:	invokevirtual	#23; //Method java/lang/Object.getClass:()Ljava/lang/Class;
   333:	ldc	#46; //String isArray
   335:	iconst_0
   336:	anewarray	#31; //class java/lang/Class
   339:	invokevirtual	#33; //Method java/lang/Class.getMethod:(Ljava/lang/String;[Ljava/lang/Class;)Ljava/lang/reflect/Method;
   342:	astore	16
   344:	aload	7
   346:	invokevirtual	#23; //Method java/lang/Object.getClass:()Ljava/lang/Class;
   349:	ldc	#47; //String isInstance
   351:	iconst_1
   352:	anewarray	#31; //class java/lang/Class
   355:	dup
   356:	iconst_0
   357:	ldc_w	#32; //class java/lang/Object
   360:	aastore
   361:	invokevirtual	#33; //Method java/lang/Class.getMethod:(Ljava/lang/String;[Ljava/lang/Class;)Ljava/lang/reflect/Method;
   364:	astore	17
   366:	aload	7
   368:	ldc	#48; //String add
   370:	iconst_2
   371:	anewarray	#31; //class java/lang/Class
   374:	dup
   375:	iconst_0
   376:	getstatic	#49; //Field java/lang/Long.TYPE:Ljava/lang/Class;
   379:	aastore
   380:	dup
   381:	iconst_1
   382:	getstatic	#49; //Field java/lang/Long.TYPE:Ljava/lang/Class;
   385:	aastore
   386:	invokevirtual	#33; //Method java/lang/Class.getMethod:(Ljava/lang/String;[Ljava/lang/Class;)Ljava/lang/reflect/Method;
   389:	astore	18
   391:	aload	7
   393:	ldc	#48; //String add
   395:	iconst_2
   396:	anewarray	#31; //class java/lang/Class
   399:	dup
   400:	iconst_0
   401:	ldc_w	#4; //class java/lang/Long
   404:	aastore
   405:	dup
   406:	iconst_1
   407:	ldc_w	#4; //class java/lang/Long
   410:	aastore
   411:	invokevirtual	#33; //Method java/lang/Class.getMethod:(Ljava/lang/String;[Ljava/lang/Class;)Ljava/lang/reflect/Method;
   414:	astore	19
   416:	aload	7
   418:	ldc	#34; //String foo
   420:	iconst_0
   421:	anewarray	#31; //class java/lang/Class
   424:	invokevirtual	#33; //Method java/lang/Class.getMethod:(Ljava/lang/String;[Ljava/lang/Class;)Ljava/lang/reflect/Method;
   427:	astore	20
   429:	getstatic	#7; //Field java/lang/System.out:Ljava/io/PrintStream;
   432:	new	#50; //class java/lang/StringBuilder
   435:	dup
   436:	invokespecial	#51; //Method java/lang/StringBuilder."<init>":()V
   439:	ldc	#52; //String toString: 
   441:	invokevirtual	#53; //Method java/lang/StringBuilder.append:(Ljava/lang/String;)Ljava/lang/StringBuilder;
   444:	aload	15
   446:	aload	7
   448:	iconst_0
   449:	anewarray	#32; //class java/lang/Object
   452:	invokevirtual	#35; //Method java/lang/reflect/Method.invoke:(Ljava/lang/Object;[Ljava/lang/Object;)Ljava/lang/Object;
   455:	invokevirtual	#54; //Method java/lang/StringBuilder.append:(Ljava/lang/Object;)Ljava/lang/StringBuilder;
   458:	invokevirtual	#55; //Method java/lang/StringBuilder.toString:()Ljava/lang/String;
   461:	invokevirtual	#9; //Method java/io/PrintStream.println:(Ljava/lang/String;)V
   464:	getstatic	#7; //Field java/lang/System.out:Ljava/io/PrintStream;
   467:	new	#50; //class java/lang/StringBuilder
   470:	dup
   471:	invokespecial	#51; //Method java/lang/StringBuilder."<init>":()V
   474:	ldc	#56; //String is array? 
   476:	invokevirtual	#53; //Method java/lang/StringBuilder.append:(Ljava/lang/String;)Ljava/lang/StringBuilder;
   479:	aload	16
   481:	aload	7
   483:	iconst_0
   484:	anewarray	#32; //class java/lang/Object
   487:	invokevirtual	#35; //Method java/lang/reflect/Method.invoke:(Ljava/lang/Object;[Ljava/lang/Object;)Ljava/lang/Object;
   490:	invokevirtual	#54; //Method java/lang/StringBuilder.append:(Ljava/lang/Object;)Ljava/lang/StringBuilder;
   493:	invokevirtual	#55; //Method java/lang/StringBuilder.toString:()Ljava/lang/String;
   496:	invokevirtual	#9; //Method java/io/PrintStream.println:(Ljava/lang/String;)V
   499:	getstatic	#7; //Field java/lang/System.out:Ljava/io/PrintStream;
   502:	new	#50; //class java/lang/StringBuilder
   505:	dup
   506:	invokespecial	#51; //Method java/lang/StringBuilder."<init>":()V
   509:	ldc	#57; //String is instance? 
   511:	invokevirtual	#53; //Method java/lang/StringBuilder.append:(Ljava/lang/String;)Ljava/lang/StringBuilder;
   514:	aload	17
   516:	aload	7
   518:	iconst_1
   519:	anewarray	#32; //class java/lang/Object
   522:	dup
   523:	iconst_0
   524:	aload	6
   526:	aastore
   527:	invokevirtual	#35; //Method java/lang/reflect/Method.invoke:(Ljava/lang/Object;[Ljava/lang/Object;)Ljava/lang/Object;
   530:	invokevirtual	#54; //Method java/lang/StringBuilder.append:(Ljava/lang/Object;)Ljava/lang/StringBuilder;
   533:	invokevirtual	#55; //Method java/lang/StringBuilder.toString:()Ljava/lang/String;
   536:	invokevirtual	#9; //Method java/io/PrintStream.println:(Ljava/lang/String;)V
   539:	new	#4; //class java/lang/Long
   542:	dup
   543:	ldc2_w	#58; //long 40l
   546:	invokespecial	#6; //Method java/lang/Long."<init>":(J)V
   549:	astore	21
   551:	new	#4; //class java/lang/Long
   554:	dup
   555:	ldc2_w	#60; //long 2l
   558:	invokespecial	#6; //Method java/lang/Long."<init>":(J)V
   561:	astore	22
   563:	getstatic	#7; //Field java/lang/System.out:Ljava/io/PrintStream;
   566:	new	#50; //class java/lang/StringBuilder
   569:	dup
   570:	invokespecial	#51; //Method java/lang/StringBuilder."<init>":()V
   573:	ldc	#62; //String unboxing: 
   575:	invokevirtual	#53; //Method java/lang/StringBuilder.append:(Ljava/lang/String;)Ljava/lang/StringBuilder;
   578:	aload	18
   580:	aconst_null
   581:	iconst_2
   582:	anewarray	#32; //class java/lang/Object
   585:	dup
   586:	iconst_0
   587:	aload	21
   589:	aastore
   590:	dup
   591:	iconst_1
   592:	aload	22
   594:	aastore
   595:	invokevirtual	#35; //Method java/lang/reflect/Method.invoke:(Ljava/lang/Object;[Ljava/lang/Object;)Ljava/lang/Object;
   598:	invokevirtual	#54; //Method java/lang/StringBuilder.append:(Ljava/lang/Object;)Ljava/lang/StringBuilder;
   601:	invokevirtual	#55; //Method java/lang/StringBuilder.toString:()Ljava/lang/String;
   604:	invokevirtual	#9; //Method java/io/PrintStream.println:(Ljava/lang/String;)V
   607:	getstatic	#7; //Field java/lang/System.out:Ljava/io/PrintStream;
   610:	new	#50; //class java/lang/StringBuilder
   613:	dup
   614:	invokespecial	#51; //Method java/lang/StringBuilder."<init>":()V
   617:	ldc	#63; //String boxing: 
   619:	invokevirtual	#53; //Method java/lang/StringBuilder.append:(Ljava/lang/String;)Ljava/lang/StringBuilder;
   622:	aload	19
   624:	aconst_null
   625:	iconst_2
   626:	anewarray	#32; //class java/lang/Object
   629:	dup
   630:	iconst_0
   631:	ldc2_w	#64; //long 1300l
   634:	invokestatic	#66; //Method java/lang/Long.valueOf:(J)Ljava/lang/Long;
   637:	aastore
   638:	dup
   639:	iconst_1
   640:	ldc2_w	#67; //long 37l
   643:	invokestatic	#66; //Method java/lang/Long.valueOf:(J)Ljava/lang/Long;
   646:	aastore
   647:	invokevirtual	#35; //Method java/lang/reflect/Method.invoke:(Ljava/lang/Object;[Ljava/lang/Object;)Ljava/lang/Object;
   650:	invokevirtual	#54; //Method java/lang/StringBuilder.append:(Ljava/lang/Object;)Ljava/lang/StringBuilder;
   653:	invokevirtual	#55; //Method java/lang/StringBuilder.toString:()Ljava/lang/String;
   656:	invokevirtual	#9; //Method java/io/PrintStream.println:(Ljava/lang/String;)V
   659:	getstatic	#7; //Field java/lang/System.out:Ljava/io/PrintStream;
   662:	new	#50; //class java/lang/StringBuilder
   665:	dup
   666:	invokespecial	#51; //Method java/lang/StringBuilder."<init>":()V
   669:	ldc	#69; //String void return: 
   671:	invokevirtual	#53; //Method java/lang/StringBuilder.append:(Ljava/lang/String;)Ljava/lang/StringBuilder;
   674:	aload	20
   676:	aconst_null
   677:	iconst_0
   678:	anewarray	#32; //class java/lang/Object
   681:	invokevirtual	#35; //Method java/lang/reflect/Method.invoke:(Ljava/lang/Object;[Ljava/lang/Object;)Ljava/lang/Object;
   684:	invokevirtual	#54; //Method java/lang/StringBuilder.append:(Ljava/lang/Object;)Ljava/lang/StringBuilder;
   687:	invokevirtual	#55; //Method java/lang/StringBuilder.toString:()Ljava/lang/String;
   690:	invokevirtual	#9; //Method java/io/PrintStream.println:(Ljava/lang/String;)V
   693:	getstatic	#7; //Field java/lang/System.out:Ljava/io/PrintStream;
   696:	ldc	#70; //String Testing java.lang.reflect.Array.set
   698:	invokevirtual	#9; //Method java/io/PrintStream.println:(Ljava/lang/String;)V
   701:	iconst_1
   702:	newarray byte
   704:	astore	23
   706:	aload	23
   708:	iconst_0
   709:	new	#71; //class java/lang/Byte
   712:	dup
   713:	iconst_1
   714:	invokespecial	#72; //Method java/lang/Byte."<init>":(B)V
   717:	invokestatic	#73; //Method java/lang/reflect/Array.set:(Ljava/lang/Object;ILjava/lang/Object;)V
   720:	getstatic	#7; //Field java/lang/System.out:Ljava/io/PrintStream;
   723:	aload	23
   725:	iconst_0
   726:	baload
   727:	invokevirtual	#74; //Method java/io/PrintStream.println:(I)V
   730:	iconst_1
   731:	newarray char
   733:	astore	24
   735:	aload	24
   737:	iconst_0
   738:	new	#75; //class java/lang/Character
   741:	dup
   742:	bipush	97
   744:	invokespecial	#76; //Method java/lang/Character."<init>":(C)V
   747:	invokestatic	#73; //Method java/lang/reflect/Array.set:(Ljava/lang/Object;ILjava/lang/Object;)V
   750:	getstatic	#7; //Field java/lang/System.out:Ljava/io/PrintStream;
   753:	aload	24
   755:	iconst_0
   756:	caload
   757:	invokevirtual	#77; //Method java/io/PrintStream.println:(C)V
   760:	iconst_1
   761:	newarray double
   763:	astore	25
   765:	aload	25
   767:	iconst_0
   768:	new	#78; //class java/lang/Double
   771:	dup
   772:	dconst_1
   773:	invokespecial	#79; //Method java/lang/Double."<init>":(D)V
   776:	invokestatic	#73; //Method java/lang/reflect/Array.set:(Ljava/lang/Object;ILjava/lang/Object;)V
   779:	getstatic	#7; //Field java/lang/System.out:Ljava/io/PrintStream;
   782:	aload	25
   784:	iconst_0
   785:	daload
   786:	invokevirtual	#80; //Method java/io/PrintStream.println:(D)V
   789:	iconst_1
   790:	newarray float
   792:	astore	26
   794:	aload	26
   796:	iconst_0
   797:	new	#81; //class java/lang/Float
   800:	dup
   801:	fconst_1
   802:	invokespecial	#82; //Method java/lang/Float."<init>":(F)V
   805:	invokestatic	#73; //Method java/lang/reflect/Array.set:(Ljava/lang/Object;ILjava/lang/Object;)V
   808:	getstatic	#7; //Field java/lang/System.out:Ljava/io/PrintStream;
   811:	aload	26
   813:	iconst_0
   814:	faload
   815:	invokevirtual	#83; //Method java/io/PrintStream.println:(F)V
   818:	iconst_1
   819:	newarray int
   821:	astore	27
   823:	aload	27
   825:	iconst_0
   826:	new	#84; //class java/lang/Integer
   829:	dup
   830:	iconst_1
   831:	invokespecial	#85; //Method java/lang/Integer."<init>":(I)V
   834:	invokestatic	#73; //Method java/lang/reflect/Array.set:(Ljava/lang/Object;ILjava/lang/Object;)V
   837:	getstatic	#7; //Field java/lang/System.out:Ljava/io/PrintStream;
   840:	aload	27
   842:	iconst_0
   843:	iaload
   844:	invokevirtual	#74; //Method java/io/PrintStream.println:(I)V
   847:	iconst_1
   848:	newarray long
   850:	astore	28
   852:	aload	28
   854:	iconst_0
   855:	new	#4; //class java/lang/Long
   858:	dup
   859:	lconst_1
   860:	invokespecial	#6; //Method java/lang/Long."<init>":(J)V
   863:	invokestatic	#73; //Method java/lang/reflect/Array.set:(Ljava/lang/Object;ILjava/lang/Object;)V
   866:	getstatic	#7; //Field java/lang/System.out:Ljava/io/PrintStream;
   869:	aload	28
   871:	iconst_0
   872:	laload
   873:	invokevirtual	#86; //Method java/io/PrintStream.println:(J)V
   876:	iconst_1
   877:	newarray short
   879:	astore	29
   881:	aload	29
   883:	iconst_0
   884:	new	#87; //class java/lang/Short
   887:	dup
   888:	iconst_1
   889:	invokespecial	#88; //Method java/lang/Short."<init>":(S)V
   892:	invokestatic	#73; //Method java/lang/reflect/Array.set:(Ljava/lang/Object;ILjava/lang/Object;)V
   895:	getstatic	#7; //Field java/lang/System.out:Ljava/io/PrintStream;
   898:	aload	29
   900:	iconst_0
   901:	saload
   902:	invokevirtual	#74; //Method java/io/PrintStream.println:(I)V
   905:	iconst_1
   906:	newarray boolean
   908:	astore	30
   910:	aload	30
   912:	iconst_0
   913:	new	#89; //class java/lang/Boolean
   916:	dup
   917:	iconst_1
   918:	invokespecial	#90; //Method java/lang/Boolean."<init>":(Z)V
   921:	invokestatic	#73; //Method java/lang/reflect/Array.set:(Ljava/lang/Object;ILjava/lang/Object;)V
   924:	getstatic	#7; //Field java/lang/System.out:Ljava/io/PrintStream;
   927:	aload	30
   929:	iconst_0
   930:	baload
   931:	invokevirtual	#91; //Method java/io/PrintStream.println:(Z)V
   934:	iconst_1
   935:	anewarray	#84; //class java/lang/Integer
   938:	astore	31
   940:	aload	31
   942:	iconst_0
   943:	new	#84; //class java/lang/Integer
   946:	dup
   947:	iconst_1
   948:	invokespecial	#85; //Method java/lang/Integer."<init>":(I)V
   951:	invokestatic	#73; //Method java/lang/reflect/Array.set:(Ljava/lang/Object;ILjava/lang/Object;)V
   954:	getstatic	#7; //Field java/lang/System.out:Ljava/io/PrintStream;
   957:	aload	31
   959:	iconst_0
   960:	aaload
   961:	invokevirtual	#23; //Method java/lang/Object.getClass:()Ljava/lang/Class;
   964:	invokevirtual	#92; //Method java/lang/Class.getName:()Ljava/lang/String;
   967:	invokevirtual	#9; //Method java/io/PrintStream.println:(Ljava/lang/String;)V
   970:	getstatic	#7; //Field java/lang/System.out:Ljava/io/PrintStream;
   973:	aload	31
   975:	iconst_0
   976:	aaload
   977:	invokevirtual	#21; //Method java/io/PrintStream.println:(Ljava/lang/Object;)V
   980:	getstatic	#7; //Field java/lang/System.out:Ljava/io/PrintStream;
   983:	ldc	#93; //String Checking Array.set's exceptions
   985:	invokevirtual	#9; //Method java/io/PrintStream.println:(Ljava/lang/String;)V
   988:	aload	24
   990:	iconst_1
   991:	new	#75; //class java/lang/Character
   994:	dup
   995:	bipush	97
   997:	invokespecial	#76; //Method java/lang/Character."<init>":(C)V
   1000:	invokestatic	#73; //Method java/lang/reflect/Array.set:(Ljava/lang/Object;ILjava/lang/Object;)V
   1003:	goto	1016
   1006:	astore	32
   1008:	getstatic	#7; //Field java/lang/System.out:Ljava/io/PrintStream;
   1011:	ldc	#95; //String Caught ArrayIndexOutOfBoundsException
   1013:	invokevirtual	#9; //Method java/io/PrintStream.println:(Ljava/lang/String;)V
   1016:	aload	24
   1018:	iconst_m1
   1019:	new	#75; //class java/lang/Character
   1022:	dup
   1023:	bipush	97
   1025:	invokespecial	#76; //Method java/lang/Character."<init>":(C)V
   1028:	invokestatic	#73; //Method java/lang/reflect/Array.set:(Ljava/lang/Object;ILjava/lang/Object;)V
   1031:	goto	1044
   1034:	astore	32
   1036:	getstatic	#7; //Field java/lang/System.out:Ljava/io/PrintStream;
   1039:	ldc	#95; //String Caught ArrayIndexOutOfBoundsException
   1041:	invokevirtual	#9; //Method java/io/PrintStream.println:(Ljava/lang/String;)V
   1044:	aload	23
   1046:	iconst_0
   1047:	new	#75; //class java/lang/Character
   1050:	dup
   1051:	bipush	97
   1053:	invokespecial	#76; //Method java/lang/Character."<init>":(C)V
   1056:	invokestatic	#73; //Method java/lang/reflect/Array.set:(Ljava/lang/Object;ILjava/lang/Object;)V
   1059:	goto	1072
   1062:	astore	32
   1064:	getstatic	#7; //Field java/lang/System.out:Ljava/io/PrintStream;
   1067:	ldc	#97; //String Caught IllegalArgumentException
   1069:	invokevirtual	#9; //Method java/io/PrintStream.println:(Ljava/lang/String;)V
   1072:	aload	31
   1074:	iconst_0
   1075:	ldc	#34; //String foo
   1077:	invokestatic	#73; //Method java/lang/reflect/Array.set:(Ljava/lang/Object;ILjava/lang/Object;)V
   1080:	goto	1093
   1083:	astore	32
   1085:	getstatic	#7; //Field java/lang/System.out:Ljava/io/PrintStream;
   1088:	ldc	#97; //String Caught IllegalArgumentException
   1090:	invokevirtual	#9; //Method java/io/PrintStream.println:(Ljava/lang/String;)V
   1093:	aload	23
   1095:	iconst_1
   1096:	new	#75; //class java/lang/Character
   1099:	dup
   1100:	bipush	97
   1102:	invokespecial	#76; //Method java/lang/Character."<init>":(C)V
   1105:	invokestatic	#73; //Method java/lang/reflect/Array.set:(Ljava/lang/Object;ILjava/lang/Object;)V
   1108:	goto	1121
   1111:	astore	32
   1113:	getstatic	#7; //Field java/lang/System.out:Ljava/io/PrintStream;
   1116:	ldc	#95; //String Caught ArrayIndexOutOfBoundsException
   1118:	invokevirtual	#9; //Method java/io/PrintStream.println:(Ljava/lang/String;)V
   1121:	getstatic	#7; //Field java/lang/System.out:Ljava/io/PrintStream;
   1124:	ldc	#98; //String Testing java.lang.reflect.Array.get*
   1126:	invokevirtual	#9; //Method java/io/PrintStream.println:(Ljava/lang/String;)V
   1129:	getstatic	#7; //Field java/lang/System.out:Ljava/io/PrintStream;
   1132:	aload	23
   1134:	invokestatic	#99; //Method java/lang/reflect/Array.getLength:(Ljava/lang/Object;)I
   1137:	invokevirtual	#74; //Method java/io/PrintStream.println:(I)V
   1140:	getstatic	#7; //Field java/lang/System.out:Ljava/io/PrintStream;
   1143:	aload	23
   1145:	iconst_0
   1146:	invokestatic	#100; //Method java/lang/reflect/Array.getByte:(Ljava/lang/Object;I)B
   1149:	invokevirtual	#74; //Method java/io/PrintStream.println:(I)V
   1152:	getstatic	#7; //Field java/lang/System.out:Ljava/io/PrintStream;
   1155:	aload	24
   1157:	iconst_0
   1158:	invokestatic	#101; //Method java/lang/reflect/Array.getChar:(Ljava/lang/Object;I)C
   1161:	invokevirtual	#77; //Method java/io/PrintStream.println:(C)V
   1164:	getstatic	#7; //Field java/lang/System.out:Ljava/io/PrintStream;
   1167:	aload	25
   1169:	iconst_0
   1170:	invokestatic	#102; //Method java/lang/reflect/Array.getDouble:(Ljava/lang/Object;I)D
   1173:	invokevirtual	#80; //Method java/io/PrintStream.println:(D)V
   1176:	getstatic	#7; //Field java/lang/System.out:Ljava/io/PrintStream;
   1179:	aload	26
   1181:	iconst_0
   1182:	invokestatic	#103; //Method java/lang/reflect/Array.getFloat:(Ljava/lang/Object;I)F
   1185:	invokevirtual	#83; //Method java/io/PrintStream.println:(F)V
   1188:	getstatic	#7; //Field java/lang/System.out:Ljava/io/PrintStream;
   1191:	aload	27
   1193:	iconst_0
   1194:	invokestatic	#104; //Method java/lang/reflect/Array.getInt:(Ljava/lang/Object;I)I
   1197:	invokevirtual	#74; //Method java/io/PrintStream.println:(I)V
   1200:	getstatic	#7; //Field java/lang/System.out:Ljava/io/PrintStream;
   1203:	aload	28
   1205:	iconst_0
   1206:	invokestatic	#105; //Method java/lang/reflect/Array.getLong:(Ljava/lang/Object;I)J
   1209:	invokevirtual	#86; //Method java/io/PrintStream.println:(J)V
   1212:	getstatic	#7; //Field java/lang/System.out:Ljava/io/PrintStream;
   1215:	aload	29
   1217:	iconst_0
   1218:	invokestatic	#106; //Method java/lang/reflect/Array.getShort:(Ljava/lang/Object;I)S
   1221:	invokevirtual	#74; //Method java/io/PrintStream.println:(I)V
   1224:	getstatic	#7; //Field java/lang/System.out:Ljava/io/PrintStream;
   1227:	aload	30
   1229:	iconst_0
   1230:	invokestatic	#107; //Method java/lang/reflect/Array.getBoolean:(Ljava/lang/Object;I)Z
   1233:	invokevirtual	#91; //Method java/io/PrintStream.println:(Z)V
   1236:	getstatic	#7; //Field java/lang/System.out:Ljava/io/PrintStream;
   1239:	aload	31
   1241:	iconst_0
   1242:	invokestatic	#108; //Method java/lang/reflect/Array.get:(Ljava/lang/Object;I)Ljava/lang/Object;
   1245:	invokevirtual	#23; //Method java/lang/Object.getClass:()Ljava/lang/Class;
   1248:	invokevirtual	#92; //Method java/lang/Class.getName:()Ljava/lang/String;
   1251:	invokevirtual	#9; //Method java/io/PrintStream.println:(Ljava/lang/String;)V
   1254:	getstatic	#7; //Field java/lang/System.out:Ljava/io/PrintStream;
   1257:	aload	27
   1259:	iconst_0
   1260:	invokestatic	#108; //Method java/lang/reflect/Array.get:(Ljava/lang/Object;I)Ljava/lang/Object;
   1263:	invokevirtual	#23; //Method java/lang/Object.getClass:()Ljava/lang/Class;
   1266:	invokevirtual	#92; //Method java/lang/Class.getName:()Ljava/lang/String;
   1269:	invokevirtual	#9; //Method java/io/PrintStream.println:(Ljava/lang/String;)V
   1272:	getstatic	#7; //Field java/lang/System.out:Ljava/io/PrintStream;
   1275:	ldc	#109; //String Checking Array.get*'s exceptions
   1277:	invokevirtual	#9; //Method java/io/PrintStream.println:(Ljava/lang/String;)V
   1280:	aload	24
   1282:	iconst_1
   1283:	invokestatic	#101; //Method java/lang/reflect/Array.getChar:(Ljava/lang/Object;I)C
   1286:	pop
   1287:	goto	1300
   1290:	astore	32
   1292:	getstatic	#7; //Field java/lang/System.out:Ljava/io/PrintStream;
   1295:	ldc	#95; //String Caught ArrayIndexOutOfBoundsException
   1297:	invokevirtual	#9; //Method java/io/PrintStream.println:(Ljava/lang/String;)V
   1300:	aload	24
   1302:	iconst_m1
   1303:	invokestatic	#101; //Method java/lang/reflect/Array.getChar:(Ljava/lang/Object;I)C
   1306:	pop
   1307:	goto	1320
   1310:	astore	32
   1312:	getstatic	#7; //Field java/lang/System.out:Ljava/io/PrintStream;
   1315:	ldc	#95; //String Caught ArrayIndexOutOfBoundsException
   1317:	invokevirtual	#9; //Method java/io/PrintStream.println:(Ljava/lang/String;)V
   1320:	return
  Exception table:
   from   to  target type
   988  1003  1006   Class java/lang/ArrayIndexOutOfBoundsException

  1016  1031  1034   Class java/lang/ArrayIndexOutOfBoundsException

  1044  1059  1062   Class java/lang/IllegalArgumentException

  1072  1080  1083   Class java/lang/IllegalArgumentException

  1093  1108  1111   Class java/lang/ArrayIndexOutOfBoundsException

  1280  1287  1290   Class java/lang/ArrayIndexOutOfBoundsException

  1300  1307  1310   Class java/lang/ArrayIndexOutOfBoundsException

  LineNumberTable: 
   line 39: 0
   line 40: 14
   line 41: 24
   line 42: 48
   line 45: 58
   line 46: 70
   line 49: 85
   line 50: 93
   line 51: 103
   line 54: 115
   line 55: 135
   line 57: 151
   line 58: 160
   line 62: 165
   line 63: 174
   line 64: 186
   line 65: 195
   line 66: 207
   line 67: 216
   line 68: 228
   line 69: 237
   line 70: 249
   line 71: 258
   line 72: 270
   line 73: 279
   line 74: 291
   line 75: 300
   line 77: 312
   line 78: 328
   line 79: 344
   line 80: 366
   line 81: 391
   line 82: 416
   line 84: 429
   line 86: 464
   line 88: 499
   line 90: 539
   line 91: 551
   line 92: 563
   line 94: 607
   line 96: 659
   line 98: 693
   line 99: 701
   line 100: 706
   line 101: 720
   line 103: 730
   line 104: 735
   line 105: 750
   line 107: 760
   line 108: 765
   line 109: 779
   line 111: 789
   line 112: 794
   line 113: 808
   line 115: 818
   line 116: 823
   line 117: 837
   line 119: 847
   line 120: 852
   line 121: 866
   line 123: 876
   line 124: 881
   line 125: 895
   line 127: 905
   line 128: 910
   line 129: 924
   line 132: 934
   line 133: 940
   line 134: 954
   line 135: 970
   line 137: 980
   line 140: 988
   line 144: 1003
   line 142: 1006
   line 143: 1008
   line 147: 1016
   line 151: 1031
   line 149: 1034
   line 150: 1036
   line 154: 1044
   line 158: 1059
   line 156: 1062
   line 157: 1064
   line 162: 1072
   line 165: 1080
   line 163: 1083
   line 164: 1085
   line 171: 1093
   line 175: 1108
   line 173: 1111
   line 174: 1113
   line 177: 1121
   line 178: 1129
   line 179: 1140
   line 180: 1152
   line 181: 1164
   line 182: 1176
   line 183: 1188
   line 184: 1200
   line 185: 1212
   line 186: 1224
   line 188: 1236
   line 190: 1254
   line 192: 1272
   line 194: 1280
   line 198: 1287
   line 196: 1290
   line 197: 1292
   line 200: 1300
   line 204: 1307
   line 202: 1310
   line 203: 1312
   line 205: 1320

  StackMapTable: number_of_entries = 14
   frame_type = 255 /* full_frame */
     offset_delta = 1006
     locals = [ class "[Ljava/lang/String;", class "[I", class "[[I", class classes/test/Reflection$SubClass, class java/lang/reflect/Field, class java/lang/reflect/Method, class classes/test/Reflection, class java/lang/Class, class java/lang/reflect/Field, class java/lang/reflect/Field, class java/lang/reflect/Field, class java/lang/reflect/Field, class java/lang/reflect/Field, class java/lang/reflect/Field, class java/lang/reflect/Field, class java/lang/reflect/Method, class java/lang/reflect/Method, class java/lang/reflect/Method, class java/lang/reflect/Method, class java/lang/reflect/Method, class java/lang/reflect/Method, class java/lang/Long, class java/lang/Long, class "[B", class "[C", class "[D", class "[F", class "[I", class "[J", class "[S", class "[Z", class "[Ljava/lang/Integer;" ]
     stack = [ class java/lang/ArrayIndexOutOfBoundsException ]
   frame_type = 9 /* same */
   frame_type = 81 /* same_locals_1_stack_item */
     stack = [ class java/lang/ArrayIndexOutOfBoundsException ]
   frame_type = 9 /* same */
   frame_type = 81 /* same_locals_1_stack_item */
     stack = [ class java/lang/IllegalArgumentException ]
   frame_type = 9 /* same */
   frame_type = 74 /* same_locals_1_stack_item */
     stack = [ class java/lang/IllegalArgumentException ]
   frame_type = 9 /* same */
   frame_type = 81 /* same_locals_1_stack_item */
     stack = [ class java/lang/ArrayIndexOutOfBoundsException ]
   frame_type = 9 /* same */
   frame_type = 247 /* same_locals_1_stack_item_frame_extended */
     offset_delta = 168
     stack = [ class java/lang/ArrayIndexOutOfBoundsException ]
   frame_type = 9 /* same */
   frame_type = 73 /* same_locals_1_stack_item */
     stack = [ class java/lang/ArrayIndexOutOfBoundsException ]
   frame_type = 9 /* same */

  Exceptions: 
   throws java.lang.ClassNotFoundException, java.lang.NoSuchMethodException, java.lang.IllegalAccessException, java.lang.reflect.InvocationTargetException, java.lang.NoSuchFieldException
}

