Compiled from "Strings.java"
public class classes.test.Strings extends java.lang.Object
  SourceFile: "Strings.java"
  minor version: 0
  major version: 50
  Constant pool:
const #1 = Method	#33.#45;	//  java/lang/Object."<init>":()V
const #2 = String	#46;	//  alphabet
const #3 = String	#47;	//  belvedere
const #4 = String	#48;	//  AlPhAbEt
const #5 = String	#49;	//    \t alphabet  \n \t 
const #6 = String	#50;	//  This has \"quotes\"
const #7 = Field	#51.#52;	//  java/lang/System.out:Ljava/io/PrintStream;
const #8 = String	#53;	//  phab
const #9 = Method	#54.#55;	//  java/lang/String.contains:(Ljava/lang/CharSequence;)Z
const #10 = Method	#56.#57;	//  java/io/PrintStream.println:(Z)V
const #11 = String	#58;	//  alpha
const #12 = Method	#54.#59;	//  java/lang/String.startsWith:(Ljava/lang/String;)Z
const #13 = String	#60;	//  bet
const #14 = Method	#54.#61;	//  java/lang/String.endsWith:(Ljava/lang/String;)Z
const #15 = Method	#54.#62;	//  java/lang/String.toUpperCase:()Ljava/lang/String;
const #16 = Method	#56.#63;	//  java/io/PrintStream.println:(Ljava/lang/String;)V
const #17 = Method	#54.#64;	//  java/lang/String.toLowerCase:()Ljava/lang/String;
const #18 = Method	#54.#65;	//  java/lang/String.equalsIgnoreCase:(Ljava/lang/String;)Z
const #19 = String	#66;	//  a
const #20 = Method	#54.#67;	//  java/lang/String.lastIndexOf:(Ljava/lang/String;)I
const #21 = Method	#56.#68;	//  java/io/PrintStream.println:(I)V
const #22 = Method	#54.#69;	//  java/lang/String.length:()I
const #23 = Method	#54.#70;	//  java/lang/String.substring:(II)Ljava/lang/String;
const #24 = Method	#54.#71;	//  java/lang/String.toString:()Ljava/lang/String;
const #25 = Method	#54.#72;	//  java/lang/String.trim:()Ljava/lang/String;
const #26 = Method	#54.#73;	//  java/lang/String.replace:(CC)Ljava/lang/String;
const #27 = Method	#54.#74;	//  java/lang/String.valueOf:(I)Ljava/lang/String;
const #28 = Method	#56.#75;	//  java/io/PrintStream.print:(I)V
const #29 = double	1.5d;
const #31 = Method	#54.#76;	//  java/lang/String.valueOf:(D)Ljava/lang/String;
const #32 = String	#77;	//  %s is asdf
const #33 = class	#78;	//  java/lang/Object
const #34 = String	#79;	//  asdf
const #35 = Method	#56.#80;	//  java/io/PrintStream.format:(Ljava/lang/String;[Ljava/lang/Object;)Ljava/io/PrintStream;
const #36 = class	#81;	//  classes/test/Strings
const #37 = Asciz	<init>;
const #38 = Asciz	()V;
const #39 = Asciz	Code;
const #40 = Asciz	LineNumberTable;
const #41 = Asciz	main;
const #42 = Asciz	([Ljava/lang/String;)V;
const #43 = Asciz	SourceFile;
const #44 = Asciz	Strings.java;
const #45 = NameAndType	#37:#38;//  "<init>":()V
const #46 = Asciz	alphabet;
const #47 = Asciz	belvedere;
const #48 = Asciz	AlPhAbEt;
const #49 = Asciz	  \t alphabet  \n \t ;
const #50 = Asciz	This has \"quotes\";
const #51 = class	#82;	//  java/lang/System
const #52 = NameAndType	#83:#84;//  out:Ljava/io/PrintStream;
const #53 = Asciz	phab;
const #54 = class	#85;	//  java/lang/String
const #55 = NameAndType	#86:#87;//  contains:(Ljava/lang/CharSequence;)Z
const #56 = class	#88;	//  java/io/PrintStream
const #57 = NameAndType	#89:#90;//  println:(Z)V
const #58 = Asciz	alpha;
const #59 = NameAndType	#91:#92;//  startsWith:(Ljava/lang/String;)Z
const #60 = Asciz	bet;
const #61 = NameAndType	#93:#92;//  endsWith:(Ljava/lang/String;)Z
const #62 = NameAndType	#94:#95;//  toUpperCase:()Ljava/lang/String;
const #63 = NameAndType	#89:#96;//  println:(Ljava/lang/String;)V
const #64 = NameAndType	#97:#95;//  toLowerCase:()Ljava/lang/String;
const #65 = NameAndType	#98:#92;//  equalsIgnoreCase:(Ljava/lang/String;)Z
const #66 = Asciz	a;
const #67 = NameAndType	#99:#100;//  lastIndexOf:(Ljava/lang/String;)I
const #68 = NameAndType	#89:#101;//  println:(I)V
const #69 = NameAndType	#102:#103;//  length:()I
const #70 = NameAndType	#104:#105;//  substring:(II)Ljava/lang/String;
const #71 = NameAndType	#106:#95;//  toString:()Ljava/lang/String;
const #72 = NameAndType	#107:#95;//  trim:()Ljava/lang/String;
const #73 = NameAndType	#108:#109;//  replace:(CC)Ljava/lang/String;
const #74 = NameAndType	#110:#111;//  valueOf:(I)Ljava/lang/String;
const #75 = NameAndType	#112:#101;//  print:(I)V
const #76 = NameAndType	#110:#113;//  valueOf:(D)Ljava/lang/String;
const #77 = Asciz	%s is asdf;
const #78 = Asciz	java/lang/Object;
const #79 = Asciz	asdf;
const #80 = NameAndType	#114:#115;//  format:(Ljava/lang/String;[Ljava/lang/Object;)Ljava/io/PrintStream;
const #81 = Asciz	classes/test/Strings;
const #82 = Asciz	java/lang/System;
const #83 = Asciz	out;
const #84 = Asciz	Ljava/io/PrintStream;;
const #85 = Asciz	java/lang/String;
const #86 = Asciz	contains;
const #87 = Asciz	(Ljava/lang/CharSequence;)Z;
const #88 = Asciz	java/io/PrintStream;
const #89 = Asciz	println;
const #90 = Asciz	(Z)V;
const #91 = Asciz	startsWith;
const #92 = Asciz	(Ljava/lang/String;)Z;
const #93 = Asciz	endsWith;
const #94 = Asciz	toUpperCase;
const #95 = Asciz	()Ljava/lang/String;;
const #96 = Asciz	(Ljava/lang/String;)V;
const #97 = Asciz	toLowerCase;
const #98 = Asciz	equalsIgnoreCase;
const #99 = Asciz	lastIndexOf;
const #100 = Asciz	(Ljava/lang/String;)I;
const #101 = Asciz	(I)V;
const #102 = Asciz	length;
const #103 = Asciz	()I;
const #104 = Asciz	substring;
const #105 = Asciz	(II)Ljava/lang/String;;
const #106 = Asciz	toString;
const #107 = Asciz	trim;
const #108 = Asciz	replace;
const #109 = Asciz	(CC)Ljava/lang/String;;
const #110 = Asciz	valueOf;
const #111 = Asciz	(I)Ljava/lang/String;;
const #112 = Asciz	print;
const #113 = Asciz	(D)Ljava/lang/String;;
const #114 = Asciz	format;
const #115 = Asciz	(Ljava/lang/String;[Ljava/lang/Object;)Ljava/io/PrintStream;;

{
public classes.test.Strings();
  Code:
   Stack=1, Locals=1, Args_size=1
   0:	aload_0
   1:	invokespecial	#1; //Method java/lang/Object."<init>":()V
   4:	return
  LineNumberTable: 
   line 3: 0


public static void main(java.lang.String[]);
  Code:
   Stack=6, Locals=8, Args_size=1
   0:	ldc	#2; //String alphabet
   2:	astore_1
   3:	ldc	#3; //String belvedere
   5:	astore_2
   6:	ldc	#4; //String AlPhAbEt
   8:	astore_3
   9:	ldc	#5; //String   \t alphabet  \n \t 
   11:	astore	4
   13:	ldc	#6; //String This has \"quotes\"
   15:	astore	5
   17:	iconst_5
   18:	istore	6
   20:	bipush	6
   22:	istore	7
   24:	getstatic	#7; //Field java/lang/System.out:Ljava/io/PrintStream;
   27:	aload_1
   28:	ldc	#8; //String phab
   30:	invokevirtual	#9; //Method java/lang/String.contains:(Ljava/lang/CharSequence;)Z
   33:	invokevirtual	#10; //Method java/io/PrintStream.println:(Z)V
   36:	getstatic	#7; //Field java/lang/System.out:Ljava/io/PrintStream;
   39:	aload_1
   40:	aload_2
   41:	invokevirtual	#9; //Method java/lang/String.contains:(Ljava/lang/CharSequence;)Z
   44:	invokevirtual	#10; //Method java/io/PrintStream.println:(Z)V
   47:	getstatic	#7; //Field java/lang/System.out:Ljava/io/PrintStream;
   50:	aload_1
   51:	ldc	#11; //String alpha
   53:	invokevirtual	#12; //Method java/lang/String.startsWith:(Ljava/lang/String;)Z
   56:	invokevirtual	#10; //Method java/io/PrintStream.println:(Z)V
   59:	getstatic	#7; //Field java/lang/System.out:Ljava/io/PrintStream;
   62:	aload_1
   63:	ldc	#13; //String bet
   65:	invokevirtual	#14; //Method java/lang/String.endsWith:(Ljava/lang/String;)Z
   68:	invokevirtual	#10; //Method java/io/PrintStream.println:(Z)V
   71:	getstatic	#7; //Field java/lang/System.out:Ljava/io/PrintStream;
   74:	aload_1
   75:	invokevirtual	#15; //Method java/lang/String.toUpperCase:()Ljava/lang/String;
   78:	invokevirtual	#16; //Method java/io/PrintStream.println:(Ljava/lang/String;)V
   81:	getstatic	#7; //Field java/lang/System.out:Ljava/io/PrintStream;
   84:	aload_1
   85:	invokevirtual	#17; //Method java/lang/String.toLowerCase:()Ljava/lang/String;
   88:	invokevirtual	#16; //Method java/io/PrintStream.println:(Ljava/lang/String;)V
   91:	getstatic	#7; //Field java/lang/System.out:Ljava/io/PrintStream;
   94:	aload_1
   95:	aload_3
   96:	invokevirtual	#18; //Method java/lang/String.equalsIgnoreCase:(Ljava/lang/String;)Z
   99:	invokevirtual	#10; //Method java/io/PrintStream.println:(Z)V
   102:	getstatic	#7; //Field java/lang/System.out:Ljava/io/PrintStream;
   105:	aload_1
   106:	ldc	#19; //String a
   108:	invokevirtual	#20; //Method java/lang/String.lastIndexOf:(Ljava/lang/String;)I
   111:	invokevirtual	#21; //Method java/io/PrintStream.println:(I)V
   114:	getstatic	#7; //Field java/lang/System.out:Ljava/io/PrintStream;
   117:	aload_1
   118:	invokevirtual	#22; //Method java/lang/String.length:()I
   121:	invokevirtual	#21; //Method java/io/PrintStream.println:(I)V
   124:	getstatic	#7; //Field java/lang/System.out:Ljava/io/PrintStream;
   127:	aload_1
   128:	iconst_4
   129:	bipush	6
   131:	invokevirtual	#23; //Method java/lang/String.substring:(II)Ljava/lang/String;
   134:	invokevirtual	#16; //Method java/io/PrintStream.println:(Ljava/lang/String;)V
   137:	getstatic	#7; //Field java/lang/System.out:Ljava/io/PrintStream;
   140:	aload_1
   141:	invokevirtual	#24; //Method java/lang/String.toString:()Ljava/lang/String;
   144:	invokevirtual	#16; //Method java/io/PrintStream.println:(Ljava/lang/String;)V
   147:	getstatic	#7; //Field java/lang/System.out:Ljava/io/PrintStream;
   150:	aload	4
   152:	invokevirtual	#16; //Method java/io/PrintStream.println:(Ljava/lang/String;)V
   155:	getstatic	#7; //Field java/lang/System.out:Ljava/io/PrintStream;
   158:	aload	4
   160:	invokevirtual	#25; //Method java/lang/String.trim:()Ljava/lang/String;
   163:	invokevirtual	#16; //Method java/io/PrintStream.println:(Ljava/lang/String;)V
   166:	getstatic	#7; //Field java/lang/System.out:Ljava/io/PrintStream;
   169:	aload	5
   171:	invokevirtual	#16; //Method java/io/PrintStream.println:(Ljava/lang/String;)V
   174:	getstatic	#7; //Field java/lang/System.out:Ljava/io/PrintStream;
   177:	aload_1
   178:	bipush	97
   180:	bipush	122
   182:	invokevirtual	#26; //Method java/lang/String.replace:(CC)Ljava/lang/String;
   185:	invokevirtual	#16; //Method java/io/PrintStream.println:(Ljava/lang/String;)V
   188:	getstatic	#7; //Field java/lang/System.out:Ljava/io/PrintStream;
   191:	iconst_1
   192:	invokestatic	#27; //Method java/lang/String.valueOf:(I)Ljava/lang/String;
   195:	invokevirtual	#16; //Method java/io/PrintStream.println:(Ljava/lang/String;)V
   198:	getstatic	#7; //Field java/lang/System.out:Ljava/io/PrintStream;
   201:	iconst_1
   202:	invokevirtual	#28; //Method java/io/PrintStream.print:(I)V
   205:	getstatic	#7; //Field java/lang/System.out:Ljava/io/PrintStream;
   208:	iconst_2
   209:	invokevirtual	#28; //Method java/io/PrintStream.print:(I)V
   212:	getstatic	#7; //Field java/lang/System.out:Ljava/io/PrintStream;
   215:	iconst_3
   216:	invokevirtual	#21; //Method java/io/PrintStream.println:(I)V
   219:	getstatic	#7; //Field java/lang/System.out:Ljava/io/PrintStream;
   222:	ldc2_w	#29; //double 1.5d
   225:	invokestatic	#31; //Method java/lang/String.valueOf:(D)Ljava/lang/String;
   228:	invokevirtual	#16; //Method java/io/PrintStream.println:(Ljava/lang/String;)V
   231:	getstatic	#7; //Field java/lang/System.out:Ljava/io/PrintStream;
   234:	ldc	#32; //String %s is asdf
   236:	iconst_1
   237:	anewarray	#33; //class java/lang/Object
   240:	dup
   241:	iconst_0
   242:	ldc	#34; //String asdf
   244:	aastore
   245:	invokevirtual	#35; //Method java/io/PrintStream.format:(Ljava/lang/String;[Ljava/lang/Object;)Ljava/io/PrintStream;
   248:	pop
   249:	return
  LineNumberTable: 
   line 5: 0
   line 6: 3
   line 7: 6
   line 8: 9
   line 9: 13
   line 10: 17
   line 11: 20
   line 13: 24
   line 14: 36
   line 15: 47
   line 16: 59
   line 17: 71
   line 18: 81
   line 19: 91
   line 20: 102
   line 21: 114
   line 22: 124
   line 23: 137
   line 24: 147
   line 25: 155
   line 26: 166
   line 27: 174
   line 28: 188
   line 30: 198
   line 31: 219
   line 32: 231
   line 33: 249


}

